Workbook

Sheet ключевые слова
A1: Введите ниже ключевые слова
A2: сбор
A3: запись
A4: систематизация
A5: накопление
A6: хранение
A7: уточнение (обновление, изменение)
A8: извлечение
A9: использование
A10: передача (распространение, предоставление, доступ)
A11: удаление
A12: уничтожение

Sheet данные для анализа
A1: поле для анализа: actions_category | B1: rkn:name_full | C1: rkn:address
A2: Сбор, систематизация, хранение, использование, уточнение (обновление, изменение), накопление, обезличивание, блокирование, уничтожение, передача в казначейство, банк, налоговую службу, федеральные фонды. | B2: федеральное государственное бюджетное образовательное учреждение высшего образования "Новосибирский государственный аграрный университет" | C2: 630039, г. Новосибирск, ул. Добролюбова, д. 160
A3: Сбор, систематизация, накопление, хранение, уточнение (обновление, изменение), использование, распространение (в том числе передача), уничтожение персональных данных. | B3: федеральное государственное бюджетное образовательное учреждение высшего профессионального образования "Волгоградский государственный архитектурно-строительный университет" | C3: 400074, Волгоградская обл., г. Волгоград, ул. Академическая, д. 1
A4: Сбор, запись, систематизация, накопление, хранение, уточнение (обновление, изменение), извлечение, использование, передача (распространение, предоставление, доступ), обезличивание, блокирование, удаление, уничтожение персональных данных. | B4: Федеральное государственное бюджетное образовательное учреждение высшего образования "Уральский государственный университет путей сообщения" | C4: 620034, Свердловская обл, Екатеринбург г, Колмогорова ул, д. 66
A5: путем смешанной обработки персональных данных с передачей информации по внутренней сети | B5: Государственное образовательное учреждение высшего профессионального образования "Московский государственный технический университет имени Н.Э.Баумана" | C5: 105005, г. Москва, ул. Бауманская 2-я, д. 5
A6: Сбор, систематизация, накопление, хранение, уточнение, распространение, обезличивание, уничтожение | B6: Государственное бюджетное образовательное учреждение высшего профессионального образования «Пермский государственный медицинский университет имени академика Е.А. Вагнера» Министерства здравоохранения Российской Федерации | C6: ул. Петропавловская, д. 26, г. Пермь, 614000
A7: смешанная обработка вышеуказанных персональных данных будет осуществляться с использованием ПЭВМ (информация доступна лишь для строго определенных сотрудников юридического лица), с передачей полученной информации по локальной сети. | B7: Федеральное государственное образовательное учреждение высшего профессионального образования "Военно-технический университет при Федеральном агентстве специального строительства" | C7: 143900, Московская обл.,г. Балашиха-11, ул. Карбышева, д. 8
A8: Формирование документации, необходимой для осуществления образовательной и научной деятельности. | B8: Государственное образовательное учреждение высшего профессионального образования "Московский государственный институт электроники и математики (технический университет)" | C8: Б.Трехсвятительский пер., д.1-3/12, стр.8, Москва, 109028
A9: Сбор, запись, систематизация, накопление, хранение, уточнение (обновление, изменение), извлечение, использование, передача, распространение, предоставление, блокирование, трансграничная передача, удаление, уничтожение персональных данных. | B9: Федеральное государственное бюджетное образовательное учреждение высшего образования "Сочинский государственный университет" | C9: 354000, Краснодарский край, г. Сочи, р-н Центральный, ул. Пластунская, д. 94
A10: сбор, запись, систематизация, накопление, хранение, уточнение (обновления, изменение), извлечение, использование, передача (распространение, предоставление, доступ), обезличивание, блокирование, удаление, уничтожение персональных данных. | B10: федеральное государственное бюджетное образовательное учреждение высшего профессионального образования "Шуйский государственный педагогический университет" | C10: 155908, Ивановская обл., г. Шуя, ул. Кооперативная, д. 24
A11: сбор, систематизация, накопление, хранение, уточнение, использование, распространение, блокирование, уничтожение | B11: Государственное автономное образовательное учреждение высшего образования Ленинградской области "Ленинградский государственный университет имени А.С. Пушкина" | C11: 196605, г. Санкт-Петербург, г. Пушкин, ш. Петербургское, д. 10
A12: Сбор, запись, систематизация, накопление, хранение, уточнение (обновление, изменение), извлечение, использование, передача (распространение, предоставление, доступ), обезличивание, блокирование, удаление, уничтожение. | B12: федеральное государственное бюджетное образовательное учреждение высшего профессионального образования "Новосибирский государственный университет экономики и управления "НИНХ" | C12: 630099, Новосибирская обл., г. Новосибирск, ул. Каменская, д. 56
... A130: обработка и хранение на информационных системах и бумажных носителях, работа с персональными документами сотрудников и студентов, ведение их личных дел и учета. | B130: Федеральное государственное бюджетное образовательное учреждение высшего профессионального образования "Оренбургский государственный педагогический университет" | C130: 460014, Оренбургская обл., г. Оренбург, ул. Советская, д. 19

Sheet разбиение по частям
A1: данные | B1: слово 1 | C1: слово 2 | D1: слово 3 | E1: слово 4 | F1: слово 5 | G1: слово 6 | H1: слово 7 | I1: слово 8 | J1: слово 9 | K1: слово 10 | L1: слово 11 | M1: слово 12 | N1: слово 13 | O1: слово 14 | P1: слово 15 | Q1: слово 16 | R1: слово 17 | S1: слово 18 | T1: слово 19 | U1: слово 20 | V1: слово 21
A2: ='данные для анализа'!A2 | B2: сбор | C2: систематизация | D2: хранение | E2: использование | F2: уточнение (обновление, изменение) | G2: накопление | H2: обезличивание | I2: блокирование | J2: уничтожение | K2: передача в казначейство | L2: банк | M2: налоговую службу | N2: федеральные фонды.
A3: ='данные для анализа'!A3 | B3: сбор | C3: систематизация | D3: накопление | E3: хранение | F3: уточнение (обновление, изменение) | G3: использование | H3: распространение (в том числе передача) | I3: уничтожение персональных данных.
A4: ='данные для анализа'!A4 | B4: сбор | C4: запись | D4: систематизация | E4: накопление | F4: хранение | G4: уточнение (обновление, изменение) | H4: извлечение | I4: использование | J4: передача (распространение, предоставление, доступ) | K4: обезличивание | L4: блокирование | M4: удаление | N4: уничтожение персональных данных.
A5: ='данные для анализа'!A5 | B5: путем смешанной обработки персональных данных с передачей информации по внутренней сети
A6: ='данные для анализа'!A6 | B6: сбор | C6: систематизация | D6: накопление | E6: хранение | F6: уточнение | G6: распространение | H6: обезличивание | I6: уничтожение
A7: ='данные для анализа'!A7 | B7: смешанная обработка вышеуказанных персональных данных будет осуществляться с использованием пэвм (информация доступна лишь для строго определенных сотрудников юридического лица) | C7: с передачей полученной информации по локальной сети.
A8: ='данные для анализа'!A8 | B8: формирование документации | C8: необходимой для осуществления образовательной и научной деятельности.
A9: ='данные для анализа'!A9 | B9: сбор | C9: запись | D9: систематизация | E9: накопление | F9: хранение | G9: уточнение (обновление, изменение) | H9: извлечение | I9: использование | J9: передача | K9: распространение | L9: предоставление | M9: блокирование | N9: трансграничная передача | O9: удаление | P9: уничтожение персональных данных.
A10: ='данные для анализа'!A10 | B10: сбор | C10: запись | D10: систематизация | E10: накопление | F10: хранение | G10: уточнение (обновления, изменение) | H10: извлечение | I10: использование | J10: передача (распространение, предоставление, доступ) | K10: обезличивание | L10: блокирование | M10: удаление | N10: уничтожение персональных данных.
A11: ='данные для анализа'!A11 | B11: сбор | C11: систематизация | D11: накопление | E11: хранение | F11: уточнение | G11: использование | H11: распространение | I11: блокирование | J11: уничтожение
A12: ='данные для анализа'!A12 | B12: сбор | C12: запись | D12: систематизация | E12: накопление | F12: хранение | G12: уточнение (обновление, изменение) | H12: извлечение | I12: использование | J12: передача (распространение, предоставление, доступ) | K12: обезличивание | L12: блокирование | M12: удаление | N12: уничтожение.
A13: ='данные для анализа'!A13 | B13: смешанная обработка
A14: ='данные для анализа'!A14 | B14: Смешанная обработка ПД с использованием ПЭВМ (информация доступна лишь для строго определенных сотрудников юридического лица) без передачи полученной информации с использованием сети общего пользования Интернет.
A15: ='данные для анализа'!A15 | B15: смешанная обработка с использованием ПК с передачей полученной информации с использованием сети общего пользования Интернет
A16: ='данные для анализа'!A16 | B16: смешанная обработка вышеуказанных персональных данных будет осуществляться с использованием пэвм (информация доступна лишь для строго определенных сотрудников юридического лица) с передачей полученной информации | C16: с использованием сети общего пользования интернет.
A17: ='данные для анализа'!A17 | B17: смешанная обработка с использованием бумажных носителей и пк | C17: с передачей полученной информации по внутренней сети учреждения и сети общего пользования интернет
A18: ='данные для анализа'!A18 | B18: сбор | C18: запись | D18: систематизация | E18: накопление | F18: хранение | G18: уточнение (обновление, изменение) | H18: извлечение | I18: использование | J18: передача (распространение, предоставление, доступ) | K18: обезличивание | L18: блокирование | M18: удаление | N18: уничтожение
A19: ='данные для анализа'!A19 | B19: смешанная обработка персональных данных с передачей данных | C19: с использованием закрытых лвс мвд россии | D19: работа с данными на категорированном компьютерном рабочем месте | E19: работа на арм эвм
A20: ='данные для анализа'!A20 | B20: сбор | C20: систематизация | D20: накопление | E20: хранение | F20: уточнение (обновление,_x000d_ изменение) | G20: использование (в том числе передача) | H20: обезличивание | I20: _x000d_ блокирование | J20: уничтожение будет осуществляться с учетом действующего_x000d_ законодательства.
A21: ='данные для анализа'!A21 | B21: прием | C21: сбор | D21: систематизация | E21: накопление | F21: использование | G21: хранение | H21: уточнение (обновление, изменение) | I21: распространение (в том числе передачу) | J21: уничтожение | K21: блокирование | L21: обезличивание
A22: ='данные для анализа'!A22 | B22: сбор | C22: запись | D22: систематизация | E22: накопление | F22: хранение | G22: уточнение | H22: использование | I22: обезличивание | J22: удаление | K22: уничтожение
A23: ='данные для анализа'!A23 | B23: сбор | C23: систематизация | D23: накопление | E23: хранение | F23: уточнение (обновление, изменение) | G23: использование | H23: распространение (в т. ч. передача) | I23: уничтожение.
A24: ='данные для анализа'!A24 | B24: сбор | C24: запись | D24: систематизация | E24: накопление | F24: хранение | G24: уточнение (обновление, изменение) | H24: извлечение | I24: использование | J24: передача (распространение, предоставление, доступ) | K24: обезличивание | L24: блокирование | M24: удаление | N24: уничтожение
A25: ='данные для анализа'!A25 | B25: обработка персональных данных осуществляется путем смешанной обработки персональных данных. информация | C25: полученная в ходе обработки персональных данных передается по внутренней (локальной) информационной сети юридического лица | D25: которая доступна для строго определенных должностных лиц спбгуэф | E25: в соответствии с приказом ректора.
A26: ='данные для анализа'!A26 | B26: сбор | C26: запись | D26: систематизация | E26: накопление | F26: хранение | G26: уточнение (обновление, изменение) | H26: извлечение | I26: использование | J26: передача (распространение, предоставление, доступ) | K26: блокирование | L26: удаление | M26: уничтожение.
A27: ='данные для анализа'!A27 | B27: сбор | C27: запись | D27: систематизация | E27: накопление | F27: хранение | G27: уточнение (обновление, изменение) | H27: извлечение | I27: использование | J27: передача (распространение, предоставление, доступ) | K27: обезличивание | L27: блокирование | M27: удаление | N27: уничтожение персональных данных.
A28: ='данные для анализа'!A28 | B28: сбор | C28: систематизация | D28: накопление | E28: хранение | F28: уточнение (обновление, изменение) | G28: использование | H28: распространение (в том числе передача) | I28: уничтожение.
A29: ='данные для анализа'!A29 | B29: Смешанная обработка
A30: ='данные для анализа'!A30 | B30: обработка персональных данных осуществляется путём смешанной обработки | C30: включающей сбор | D30: систематизацию | E30: накопление | F30: хранение | G30: уточнение и использование с передачей информации по внутренней сети двгту в специально выделенных помещениях с использованием программных средств аутентификации и авторизации пользователями | H30: включенными в список лиц | I30: допущенных к обработке персональных данных
A31: ='данные для анализа'!A31 | B31: неавтоматизированная обработка — ведение трудовых книжек | C31: личных дел | D31: договоров | E31: списков сотрудников и обучающихся | F31: картотек со сведениями о сотрудниках | G31: картотек со сведениями о студентах | H31: журналов учебных групп | I31: автоматизированная обработка - внесение персональных данных работников в информационные системы: система организации приемной компании ис уз «модус» (подсистема «абитуриент») | J31: автоматизированная информационная библиотечная система марк-sql | K31: автоматизированная система документооборота «дело-предприятие» | L31: система расчета и начисления зарплаты сотрудникам «амба» | M31: система расчета стипендии «амба» | N31: система ведения кадрового учета и расчета зарплаты «контур-персонал» | O31: автоматизированная система бухгалтерского учета для бюджетных учреждений «парус бухгалтерия» | P31: операции с персональными данными - сбор | Q31: хранение | R31: накопление | S31: уточнение | T31: использование | U31: передача | V31: уничтожение данных
A32: ='данные для анализа'!A32 | B32: сбор | C32: запись | D32: систематизация | E32: накопление | F32: хранение | G32: уточнение (обновление, изменени) | H32: извлечение | I32: использование | J32: передача (распространение, предоставление, доступ) | K32: блокирование | L32: удаление | M32: уничтожение персональных данных.
A33: ='данные для анализа'!A33 | B33: сбор | C33: запись | D33: систематизация | E33: накопление | F33: хранение | G33: уточнение (обновление, изменение) | H33: извлечение | I33: использование | J33: передача (распространение, предоставление, доступ) | K33: обезличивание | L33: блокирование | M33: удаление | N33: уничтожение персональных данных
A34: ='данные для анализа'!A34 | B34: смешанная обработка персональных данных с передачей информации по внутренней защищенной локальной сети университета без выхода во внешние сети | C34: передача деперсонализированных общедоступных данных в открытые системы: государственные организации по сбору статистики | D34: вышестоящие федеральные организации | E34: передача данных в организации: банки | F34: налоговая служба | G34: пенсионный фонд | H34: казначейство | I34: государственные организации по сбору статистики | J34: вышестоящие федеральные организации
A35: ='данные для анализа'!A35 | B35: осуществляется смешанная обработка персональных данных
A36: ='данные для анализа'!A36 | B36: сбор | C36: систематизация | D36: накопление | E36: хранение | F36: уточнение (обновление, изменение) | G36: использование | H36: распространение | I36: обезличивание | J36: блокирование | K36: уничтожение
A37: ='данные для анализа'!A37 | B37: сбор | C37: запись | D37: систематизация | E37: накопление | F37: хранение | G37: уточнение | H37: (обновление, изменение) | I37: извлечение | J37: использование | K37: передача (предоставление) | L37: блокирование | M37: удаление | N37: уничтожение. обработка персональных данных будет осуществляться путем смешанной обработки.
A38: ='данные для анализа'!A38 | B38: сбор | C38: запись | D38: систематизация | E38: накопление | F38: хранение | G38: уточнение (обновление, изменение) | H38: извлечение | I38: использование | J38: передача (распространение, предоставление, доступ) | K38: обезличивание | L38: блокирование | M38: удаление | N38: уничтожение
A39: ='данные для анализа'!A39 | B39: сбор | C39: запись | D39: систематизация | E39: накопление | F39: хранение | G39: уточнение (обновление,изменение) | H39: извлечение | I39: использование | J39: передача (распространение, предоставление, доступ) | K39: обезличивание | L39: блокирование | M39: удаление. уничтожение персональных данных.
A40: ='данные для анализа'!A40 | B40: сбор | C40: запись | D40: систематизация | E40: накопление | F40: хранение | G40: уточнение (обновление, изменение) | H40: извлечение | I40: использование | J40: передача (распространение, предоставление, доступ) | K40: обезличивание | L40: блокирование | M40: удаление | N40: уничтожение персональных данных.
A41: ='данные для анализа'!A41 | B41: обработка: прием | C41: сбор | D41: запись | E41: систематизация | F41: накопление | G41: использование | H41: хранение | I41: уточнение (изменение, обновление) | J41: передача (распространение, предоставление, доступ) | K41: извлечение | L41: уничтожение | M41: блокирование | N41: обезличивание.
A42: ='данные для анализа'!A42 | B42: сбор | C42: накопление | D42: хранение | E42: уточнение (обновление, изменение) | F42: использование | G42: уничтожение персональных данных
A43: ='данные для анализа'!A43 | B43: сбор | C43: систематизация | D43: накопление | E43: хранение | F43: уточнение (обновление, изменение) | G43: использование | H43: обезличивание | I43: блокирование | J43: уничтожение персональных данных
A44: ='данные для анализа'!A44 | B44: сбор | C44: запись | D44: систематизация | E44: накопление | F44: хранение | G44: уточнение (обновление, изменение) | H44: извлечение | I44: использование | J44: передача (распространение, предоставление, доступ) | K44: обезличивание | L44: блокирование | M44: удаление | N44: уничтожение персональных данных
A45: ='данные для анализа'!A45 | B45: cбор | C45: систематизация | D45: накопление | E45: хранение | F45: уточнение (обновление, изменение) | G45: использование | H45: распространение (в т.ч. передача) | I45: обезличивание | J45: блокирование | K45: уничтожение персональных данных.
A46: ='данные для анализа'!A46 | B46: сбор | C46: запись | D46: систематизация | E46: накопление | F46: хранение | G46: уточнение (обновление, изменение) | H46: извлечение | I46: использование | J46: передача (распространение, предоставление, доступа) | K46: обезличивание | L46: блокирование | M46: удаление | N46: уничтожение персональных данных
A47: ='данные для анализа'!A47 | B47: сбор | C47: систематизация | D47: накопление | E47: хранение | F47: уточнение (обновление, изменение) | G47: ис-пользование | H47: передача в территориальные органы фонда обязательного медицинского стра-хования | I47: территориальные органы фонда социального страхования рф | J47: территориальные органы пенсионного фонда российской федерации | K47: территориальные органы фнс россии | L47: региональные отделения сбербанка россии | M47: военные комиссариаты
A48: ='данные для анализа'!A48 | B48: сбор | C48: запись | D48: систематизация | E48: накопление | F48: хранение | G48: уточнение | H48: (обновление, изменение) | I48: извлечение | J48: использование | K48: передача (распространение, предоставление, доступ) | L48: блокирование | M48: удаление | N48: уничтожение.
A49: ='данные для анализа'!A49 | B49: применяется смешанная обработка персональных данных
A50: ='данные для анализа'!A50 | B50: сбора | C50: обработки | D50: систематизации | E50: хранения
A51: ='данные для анализа'!A51 | B51: сбор | C51: запись | D51: систематизация | E51: накопление | F51: хранение | G51: уточнение (обновление, изменение) | H51: извле-чение | I51: использование | J51: передача (распространение, предоставление, доступ) | K51: обезличивание | L51: бло-кирование | M51: удаление | N51: уничтожение персональных данных
A52: ='данные для анализа'!A52 | B52: сбор | C52: запись | D52: систематизация | E52: накопление | F52: хранение | G52: уточнение (обновление, изменение) | H52: извлечение | I52: использование | J52: передачу (распространение, предоставление, доступ) | K52: блокирование | L52: удаление | M52: уничтожение персональных данных.
A53: ='данные для анализа'!A53 | B53: сбор | C53: запись | D53: систематизацию | E53: накопление | F53: хранение | G53: уточнение (обновление, изменение) | H53: извлечение | I53: использование | J53: передачу (предоставление, доступ) | K53: обезличивание | L53: блокирование | M53: удаление | N53: уничтожение. такие действия как использование | O53: уточнение (обновление, изменение) | P53: передача | Q53: обезличивание | R53: блокирование | S53: уничтожение осуществляются с использованием персонального компьютера при непосредственном участии человека
A54: ='данные для анализа'!A54 | B54: сбор | C54: систематизация | D54: накопление | E54: хранение | F54: уточнение (обновление, изменение) | G54: использование | H54: распространение (в том числе передача) | I54: блокирование | J54: уничтожение персональных данных
A55: ='данные для анализа'!A55 | B55: сбор | C55: систематизация | D55: накопление | E55: хранение | F55: уточнение | G55: копирование | H55: удаление | I55: обновление | J55: изменение | K55: использование | L55: распространение (передача) | M55: обезличивание | N55: блокирование | O55: уничтожение | P55: извлечение.
A56: ='данные для анализа'!A56 | B56: сбор | C56: хранение | D56: уточнение | E56: передача
A57: ='данные для анализа'!A57 | B57: сбор | C57: запись | D57: систематизацию | E57: накопление | F57: хранение | G57: уточнение (обновление, изменение) | H57: извлечение | I57: использование | J57: передачу (распространение, предоставление, доступ) | K57: обезличивание | L57: блокирование | M57: удаление | N57: уничтожение | O57: персональных данных
A58: ='данные для анализа'!A58 | B58: сбор | C58: систематизация | D58: накопление | E58: хранение | F58: уточнение (обновление, изменение) | G58: использование | H58: распространение (в том числе передача) | I58: обезличивание | J58: блокирование | K58: уничтожение
A59: ='данные для анализа'!A59 | B59: ведение трудовых книжек | C59: _x000d_ ведение личных дел на работников университета | D59: _x000d_ ведение личных дел студентов университета | E59: _x000d_ учет и хранение договоров | F59: заключенных с физическими лицами: заказчиками и потребителями | G59: _x000d_ учет и хранение государственных контрактов на оказание преподавательских услуг.
A60: ='данные для анализа'!A60 | B60: сбор | C60: систематизация | D60: накопление | E60: хранение | F60: обновление | G60: изменение | H60: использование | I60: обезличивание | J60: блокирование | K60: уничтожение | L60: в том числе посредством внесения их в электронную базу данных | M60: включения в списки (реестры) и отчетные формы | N60: предусмотренные документами | O60: регламентирующими предоставление отчетных данных (документов) передаваемых по локальной сети юридического лица и по сети интернет в части сдачи налоговой и бухгалтерской отчетности и начисления взносов на обязательное пенсионное страхование
A61: ='данные для анализа'!A61 | B61: сбор | C61: систематизация | D61: накопление | E61: хранение | F61: уточнение (обновление, изменение) | G61: _x000d_ использование | H61: распространение (в том числе передача) | I61: обезличивание | J61: блокирование | K61: _x000d_ уничтожение персональных данных.
A62: ='данные для анализа'!A62 | B62: сбор | C62: систематизация | D62: накопление | E62: хранение | F62: уточнение (обновление, изменение) | G62: использование | H62: передача (распространение, предоставление, доступ) | I62: обезличивание | J62: блокирование | K62: удаление | L62: уничтожение
A63: ='данные для анализа'!A63 | B63: путем: смешанной обработки персональных данных. информация передается по внутренней сети организации | C63: доступ к информации имеет ограниченный круг должностных лиц.
A64: ='данные для анализа'!A64 | B64: неавтоматизированная обработка-ведение трудовых книжек | C64: личных дел | D64: журналов | E64: отчётов | F64: анкет | G64: заявлений договоров | H64: автоматизированная обработка - внесение в испдн: «корпоративная информационная система башгу» | I64: «сайт» башгу | J64: «скуд башгу» | K64: операции с персональными данными: сбор | L64: запись | M64: систематизация | N64: накопление | O64: хранение | P64: уточнение (обновление, изменение) | Q64: извлечение | R64: использование | S64: передачу | T64: обезличивание | U64: блокирование | V64: удаление | W64: уничтожение
A65: ='данные для анализа'!A65 | B65: сбор | C65: систематизация | D65: накопление | E65: хранение | F65: уточнение (обновление, изменение) | G65: использование | H65: распространение (в т. ч. передача) | I65: уничтожение.
A66: ='данные для анализа'!A66 | B66: сбор | C66: запись | D66: систематизация | E66: накопление | F66: хранение | G66: уточнение (обновление, изменение) | H66: извлечение | I66: использования | J66: передача (распространение, предоставление, доступ) | K66: обезличивание | L66: блокирование | M66: удаление | N66: уничтожение.
A67: ='данные для анализа'!A67 | B67: смешанная обработка данных с передачей информации по линиям связи
A68: ='данные для анализа'!A68 | B68: сбор | C68: хранение | D68: обновление
A69: ='данные для анализа'!A69 | B69: сбор | C69: запись | D69: систематизация | E69: накопление | F69: хранение | G69: уточнение (обновление, изменение) | H69: извлечение | I69: использование | J69: передача (распространение, предоставление, доступ) | K69: блокирование | L69: удаление | M69: уничтожение персональных данных.
A70: ='данные для анализа'!A70 | B70: смешанная | C70: с передачей по внутренней сети юридического лица | D70: без передачи по сети_x000d_ интернет
A71: ='данные для анализа'!A71 | B71: ведения трудовых книжек | C71: личных дел работников и обучающихся | D71: внесения информации в информационные системы департамента образования города москвы и общегородские информационные системы | E71: хранения | F71: систематизации | G71: уточнения | H71: блокирования | I71: уничтожения персональных данных | J71: передачи персональных данных третьим лицам только на основании федеральных законов | K71: устанавливающих цель | L71: условия получения персональных данных и круг субъектов персональных данных | M71: обеспечения предоставления социального пакета
A72: ='данные для анализа'!A72 | B72: фгбоу впо "агу" осуществляет следующие действия | C72: совершаемые с персональными данными | D72: включая сбор | E72: запись | F72: систематизацию | G72: накопление | H72: хранение | I72: уточнение (обновление, изменение) | J72: извлечение | K72: использование | L72: передачу (распространение, предоставление, доступ) | M72: обезличивание | N72: блокирование | O72: удаление | P72: уничтожение | Q72: персональных данных.
A73: ='данные для анализа'!A73 | B73: сбор | C73: систематизация | D73: накопление | E73: хранение | F73: уточнение (обновление, изменение) | G73: использование | H73: передача | I73: уничтожение.
A74: ='данные для анализа'!A74 | B74: Смешанная обработка
A75: ='данные для анализа'!A75 | B75: сбор | C75: систематизация | D75: накопление | E75: хранение | F75: уточнение (обновление, изменение) | G75: использование | H75: распространение (в том числе передача) | I75: обезличивание | J75: блокирование и уничтожение.
A76: ='данные для анализа'!A76 | B76: регистрация данных
A77: ='данные для анализа'!A77 | B77: сбор | C77: запись | D77: систематизация | E77: накопление | F77: хранение | G77: уточнение (изменение, обновление) | H77: использование | I77: передача | J77: обезличивание | K77: блокирование | L77: удаление | M77: уничтожение
A78: ='данные для анализа'!A78 | B78: обработка вышеуказанных персональных данных будет осуществляться путем: сбора | C78: записи | D78: систематизации | E78: накопления | F78: хранения | G78: уточнения (обновления, изменения) | H78: извлечения | I78: использования | J78: передачи (распространения, предоставления, доступа) | K78: обезличивания | L78: блокировки | M78: удаления | N78: уничтожения персональных данных.
A79: ='данные для анализа'!A79 | B79: неавтоматизированная обработка - ведение трудовых книжек | C79: личных дел | D79: журналов | E79: отчётов | F79: договоров | G79: автоматизированная обработка - внесение персональных данных в информационную систему испдн угнту | H79: операции с персональными данными: сбор | I79: запись | J79: систематизация | K79: накопление | L79: хранение | M79: уточнение (обновление, изменение!, извлечение, использование, передача /предоставление, доступ!, блокирование, удаление, уничтожение персональных данных
A80: ='данные для анализа'!A80 | B80: сбор | C80: запись | D80: систематизацию | E80: накопление | F80: хранение | G80: уточнение (обновление, изменение) | H80: извлечение | I80: использование | J80: передачу (распространение, предоставление, доступ) | K80: обезличивание | L80: блокирование | M80: удаление | N80: уничтожение
A81: ='данные для анализа'!A81 | B81: сбор | C81: запись | D81: систематизация | E81: накопление | F81: хранение | G81: уточнение (обновление, изменение) | H81: извлечение | I81: использование | J81: передача (распространение, предоставление, доступ) | K81: обезличивание | L81: блокирование | M81: удаление | N81: уничтожение
A82: ='данные для анализа'!A82 | B82: сбор | C82: анализ | D82: обобщение | E82: хранение | F82: изменение | G82: дополнение | H82: передача | I82: уничтожение.
A83: ='данные для анализа'!A83 | B83: сбор | C83: запись | D83: накопление | E83: хранение | F83: обновление | G83: изменения
A84: ='данные для анализа'!A84 | B84: обработка вышеуказанных персональных данных будет осуществляться путем сбора | C84: записи | D84: систематизации | E84: накопления | F84: хранения | G84: уточнения (обновления, изменения) | H84: извлечения | I84: использования | J84: передачи (распространения, предоставления, доступа) | K84: обезличивания | L84: блокирования | M84: удаления | N84: уничтожения персональных данных.
A85: ='данные для анализа'!A85 | B85: обработка вышеуказанных персональных данных будет осуществляться путем: смешанная обработка персональных данных с передачей информации по внутренним защищенным локальным сетям юргпу(нпи) без выхода во внешние сети | C85: неавтоматизированная обработка персональных данных | D85: смешанная обработка общедоступных персональных данных | E85: передача деперсонализированных общедоступных данных в открытые системы | F85: передача деперсонализированных статистических данных в открытые системы: государственные организации по сбору статистики | G85: вышестоящие федеральные организации | H85: передача данных в организации: банки | I85: налоговая служба | J85: пенсионный фонд | K85: казначейство | L85: государственные организации по сбору статистики | M85: вышестоящие федеральные организации. университет при обработке персональных данных принимает все необходимые правовые | N85: организационные и технические меры для их защиты от неправомерного или случайного доступа | O85: уничтожения | P85: изменения | Q85: блокирования | R85: копирования | S85: предоставления | T85: распространения | U85: а также от иных неправомерных действий в отношении них.
A86: ='данные для анализа'!A86 | B86: сбор | C86: систематизация | D86: накопление | E86: хранение | F86: уточнение (обновление, изменение) | G86: использование | H86: распространение (в том числе передача) | I86: обезличивание | J86: блокирование | K86: уничтожение персональных данных.
A87: ='данные для анализа'!A87 | B87: осуществляется путем: сбора | C87: записи | D87: систематизации | E87: накопления | F87: хранения | G87: уточнения (обновления, изменения) | H87: использования | I87: передачи (распространения, предоставления, доступа) | J87: обезличивания | K87: блокирования | L87: удаления | M87: уничтожения персональных данных.
A88: ='данные для анализа'!A88 | B88: осуществляется путем: сбора | C88: записи | D88: систематизации | E88: накопления | F88: хранения | G88: уточнения (обновления, изменения) | H88: использования | I88: передачи (распространения, предоставления, доступа) | J88: обезличивания | K88: блокирования | L88: удаления | M88: уничтожения персональных данных.
A89: ='данные для анализа'!A89 | B89: автоматизировано с использованием биллинговой системы bg billing | C89: автоматизированных систем (внутренние системы хранения "1с: бухгалтерия государственных учреждений", "1с: университет", "1с: камин. заработная плата"). данные включают сбор | D89: запись | E89: систематизацию | F89: накопление | G89: хранение | H89: уточнение | I89: извлечение | J89: использование | K89: удаление | L89: уничтожение персональных данных и доступны только ряду ответственных сотрудников. неавтоматизированная обработка включает в себя работу с договорами | M89: трудовыми книжками | N89: бумажной картотекой сотрудников и студентов.
A90: ='данные для анализа'!A90 | B90: сбор | C90: запись | D90: систематизация | E90: накопление | F90: хранение | G90: уточнение (обновление, изменение) | H90: извлечение | I90: использование | J90: передача (распространение, предоставление, доступ) | K90: обезличивание | L90: блокирование | M90: удаление | N90: уничтожение
A91: ='данные для анализа'!A91 | B91: сбор | C91: запись | D91: хранение | E91: уточнение (обновление, изменение) | F91: использование | G91: передача (предоставление) | H91: удаление.
A92: ='данные для анализа'!A92 | B92: сбор | C92: систематизация | D92: накопление | E92: хранение | F92: уточнение (обновление, изменение) | G92: использование | H92: передача | I92: уничтожение. смешанная обработка вышеуказанных персональных данных осуществляется с использованием автоматизированных систем обработки данных | J92: с передачей полученной информации по внутренней локальной вычислительной сети и с использованием сети интернет.
A93: ='данные для анализа'!A93 | B93: обработка вышеуказанных персональных данных будет осуществляться путем смешанной обработки персональных данных с передачей полученной в ходе обработки персональных данных информации по внутренней сети нияу мифи (информация доступна лишь для строго определенных сотрудников юридического лица) | C93: в т.ч. с использованием сети общего пользования.
A94: ='данные для анализа'!A94 | B94: сбор | C94: систематизация | D94: накопление | E94: хранение | F94: уточнение (обновление, изменение использования, распространение) | G94: в том числе передача), обезличивание, блокирование, уничтожение персональных данных)
A95: ='данные для анализа'!A95 | B95: сбор | C95: запись | D95: систематизация | E95: накопление | F95: хранение | G95: уточнение (обновление, изменение) | H95: извлечение | I95: использование | J95: передача (распространение, предоставление, доступ) | K95: обезличивание | L95: блокирование | M95: удаление | N95: уничтожение.
A96: ='данные для анализа'!A96 | B96: сбор | C96: накопление | D96: хранение | E96: уточнение (обновление, изменение) | F96: систематизация | G96: использование | H96: распространение (в том числе передача) | I96: обезличивание | J96: блокирование | K96: уничтожение персональных данных | L96: необходимых для ведения образовательной и административно-хозяйственной деятельности. обмен (прием, передача) персональными данными между аггпу им. в.м. шукшина и третьими лицами (организациями) в соответствии с заключенными между ними договорами и соглашениями | M96: в целях соблюдения законных прав и интересов субъекта персональных данных.
A97: ='данные для анализа'!A97 | B97: сбор | C97: запись | D97: систематизация | E97: накопление | F97: хранение | G97: уточнение (обновление, изменение) | H97: извлечение | I97: использование | J97: передача (распространение, предоставление, доступ) | K97: обезличивание | L97: блокирование | M97: удаление | N97: уничтожение персональных данных
A98: ='данные для анализа'!A98 | B98: сбор | C98: запись | D98: систематизация | E98: накопление | F98: хранение | G98: уточнение (обновление, изменение) | H98: извлечение | I98: использование | J98: передача (в том числе трансграничная) | K98: доступ и предоставление указанным в настоящем согласии организациям | L98: обезличивание | M98: блокирование | N98: удаление | O98: уничтожение.
A99: ='данные для анализа'!A99 | B99: неавтоматизированная обработка - ведение трудовых книжек | C99: личных дел | D99: журналов | E99: отчётов | F99: договоров | G99: автоматизированная обработка - внесение персональных данных в информационные системы 1c | H99: пфр | I99: скуд | J99: спринт | K99: деканат | L99: операции с персональными данными: сбор | M99: хранение | N99: накопление | O99: уточнение | P99: передача | Q99: уничтожение данных
A100: ='данные для анализа'!A100 | B100: сбора | C100: записи | D100: систематизации | E100: накопления | F100: хранения | G100: уточнения (обновления, изменения) | H100: извлечения | I100: использования | J100: передачи (распространения, предоставления, доступа) | K100: блокирования | L100: удаления | M100: уничтожения персональных данных
...

Sheet разбиение по частям (отфильтр)
A1: данные | B1: слово 1 | C1: слово 2 | D1: слово 3 | E1: слово 4 | F1: слово 5 | G1: слово 6 | H1: слово 7 | I1: слово 8 | J1: слово 9 | K1: слово 10 | L1: слово 11 | M1: слово 12 | N1: слово 13 | O1: слово 14 | P1: слово 15 | Q1: слово 16 | R1: слово 17 | S1: слово 18 | T1: слово 19 | U1: слово 20 | V1: слово 21
A2: ='данные для анализа'!A2 | B2: сбор | C2: систематизация | D2: хранение | E2: использование | F2: уточнение (обновление, изменение) | G2: накопление | H2: обезличивание | I2: блокирование | J2: уничтожение | K2: передача в казначейство | L2: банк | M2: налоговую службу | N2: федеральные фонды
A3: ='данные для анализа'!A3 | B3: сбор | C3: систематизация | D3: накопление | E3: хранение | F3: уточнение (обновление, изменение) | G3: использование | H3: распространение (в том числе передача) | I3: уничтожение персональных данных
A4: ='данные для анализа'!A4 | B4: сбор | C4: запись | D4: систематизация | E4: накопление | F4: хранение | G4: уточнение (обновление, изменение) | H4: извлечение | I4: использование | J4: передача (распространение, предоставление, доступ) | K4: обезличивание | L4: блокирование | M4: удаление | N4: уничтожение персональных данных
A5: ='данные для анализа'!A5 | B5: путем смешанной обработки персональных данных с передачей информации по внутренней сети
A6: ='данные для анализа'!A6 | B6: сбор | C6: систематизация | D6: накопление | E6: хранение | F6: уточнение | G6: распространение | H6: обезличивание | I6: уничтожение
A7: ='данные для анализа'!A7 | B7: смешанная обработка вышеуказанных персональных данных будет осуществляться с использованием пэвм (информация доступна лишь для строго определенных сотрудников юридического лица) | C7: с передачей полученной информации по локальной сети
A8: ='данные для анализа'!A8 | B8: формирование документации | C8: необходимой для осуществления образовательной и научной деятельности
A9: ='данные для анализа'!A9 | B9: сбор | C9: запись | D9: систематизация | E9: накопление | F9: хранение | G9: уточнение (обновление, изменение) | H9: извлечение | I9: использование | J9: передача | K9: распространение | L9: предоставление | M9: блокирование | N9: трансграничная передача | O9: удаление | P9: уничтожение персональных данных
A10: ='данные для анализа'!A10 | B10: сбор | C10: запись | D10: систематизация | E10: накопление | F10: хранение | G10: уточнение (обновления, изменение) | H10: извлечение | I10: использование | J10: передача (распространение, предоставление, доступ) | K10: обезличивание | L10: блокирование | M10: удаление | N10: уничтожение персональных данных
A11: ='данные для анализа'!A11 | B11: сбор | C11: систематизация | D11: накопление | E11: хранение | F11: уточнение | G11: использование | H11: распространение | I11: блокирование | J11: уничтожение
A12: ='данные для анализа'!A12 | B12: сбор | C12: запись | D12: систематизация | E12: накопление | F12: хранение | G12: уточнение (обновление, изменение) | H12: извлечение | I12: использование | J12: передача (распространение, предоставление, доступ) | K12: обезличивание | L12: блокирование | M12: удаление | N12: уничтожение
A13: ='данные для анализа'!A13 | B13: смешанная обработка
A14: ='данные для анализа'!A14 | B14: Смешанная обработка ПД с использованием ПЭВМ (информация доступна лишь для строго определенных сотрудников юридического лица) без передачи полученной информации с использованием сети общего пользования Интернет
A15: ='данные для анализа'!A15 | B15: смешанная обработка с использованием ПК с передачей полученной информации с использованием сети общего пользования Интернет
A16: ='данные для анализа'!A16 | B16: смешанная обработка вышеуказанных персональных данных будет осуществляться с использованием пэвм (информация доступна лишь для строго определенных сотрудников юридического лица) с передачей полученной информации | C16: с использованием сети общего пользования интернет
A17: ='данные для анализа'!A17 | B17: смешанная обработка с использованием бумажных носителей и пк | C17: с передачей полученной информации по внутренней сети учреждения и сети общего пользования интернет
A18: ='данные для анализа'!A18 | B18: сбор | C18: запись | D18: систематизация | E18: накопление | F18: хранение | G18: уточнение (обновление, изменение) | H18: извлечение | I18: использование | J18: передача (распространение, предоставление, доступ) | K18: обезличивание | L18: блокирование | M18: удаление | N18: уничтожение
A19: ='данные для анализа'!A19 | B19: смешанная обработка персональных данных с передачей данных | C19: с использованием закрытых лвс мвд россии | D19: работа с данными на категорированном компьютерном рабочем месте | E19: работа на арм эвм
A20: ='данные для анализа'!A20 | B20: сбор | C20: систематизация | D20: накопление | E20: хранение | F20: уточнение (обновление,_xd_ изменение) | G20: использование (в том числе передача) | H20: обезличивание | I20: _xd_ блокирование | J20: уничтожение будет осуществляться с учетом действующего_xd_ законодательства
A21: ='данные для анализа'!A21 | B21: прием | C21: сбор | D21: систематизация | E21: накопление | F21: использование | G21: хранение | H21: уточнение (обновление, изменение) | I21: распространение (в том числе передачу) | J21: уничтожение | K21: блокирование | L21: обезличивание
A22: ='данные для анализа'!A22 | B22: сбор | C22: запись | D22: систематизация | E22: накопление | F22: хранение | G22: уточнение | H22: использование | I22: обезличивание | J22: удаление | K22: уничтожение
A23: ='данные для анализа'!A23 | B23: сбор | C23: систематизация | D23: накопление | E23: хранение | F23: уточнение (обновление, изменение) | G23: использование | H23: распространение (в т ч передача) | I23: уничтожение
A24: ='данные для анализа'!A24 | B24: сбор | C24: запись | D24: систематизация | E24: накопление | F24: хранение | G24: уточнение (обновление, изменение) | H24: извлечение | I24: использование | J24: передача (распространение, предоставление, доступ) | K24: обезличивание | L24: блокирование | M24: удаление | N24: уничтожение
A25: ='данные для анализа'!A25 | B25: обработка персональных данных осуществляется путем смешанной обработки персональных данных информация | C25: полученная в ходе обработки персональных данных передается по внутренней (локальной) информационной сети юридического лица | D25: которая доступна для строго определенных должностных лиц спбгуэф | E25: в соответствии с приказом ректора
A26: ='данные для анализа'!A26 | B26: сбор | C26: запись | D26: систематизация | E26: накопление | F26: хранение | G26: уточнение (обновление, изменение) | H26: извлечение | I26: использование | J26: передача (распространение, предоставление, доступ) | K26: блокирование | L26: удаление | M26: уничтожение
A27: ='данные для анализа'!A27 | B27: сбор | C27: запись | D27: систематизация | E27: накопление | F27: хранение | G27: уточнение (обновление, изменение) | H27: извлечение | I27: использование | J27: передача (распространение, предоставление, доступ) | K27: обезличивание | L27: блокирование | M27: удаление | N27: уничтожение персональных данных
A28: ='данные для анализа'!A28 | B28: сбор | C28: систематизация | D28: накопление | E28: хранение | F28: уточнение (обновление, изменение) | G28: использование | H28: распространение (в том числе передача) | I28: уничтожение
A29: ='данные для анализа'!A29 | B29: Смешанная обработка
A30: ='данные для анализа'!A30 | B30: обработка персональных данных осуществляется путём смешанной обработки | C30: включающей сбор | D30: систематизацию | E30: накопление | F30: хранение | G30: уточнение и использование с передачей информации по внутренней сети двгту в специально выделенных помещениях с использованием программных средств аутентификации и авторизации пользователями | H30: включенными в список лиц | I30: допущенных к обработке персональных данных
A31: ='данные для анализа'!A31 | B31: неавтоматизированная обработка — ведение трудовых книжек | C31: личных дел | D31: договоров | E31: списков сотрудников и обучающихся | F31: картотек со сведениями о сотрудниках | G31: картотек со сведениями о студентах | H31: журналов учебных групп | I31: автоматизированная обработка - внесение персональных данных работников в информационные системы: система организации приемной компании ис уз «модус» (подсистема «абитуриент») | J31: автоматизированная информационная библиотечная система марк-sql | K31: автоматизированная система документооборота «дело-предприятие» | L31: система расчета и начисления зарплаты сотрудникам «амба» | M31: система расчета стипендии «амба» | N31: система ведения кадрового учета и расчета зарплаты «контур-персонал» | O31: автоматизированная система бухгалтерского учета для бюджетных учреждений «парус бухгалтерия» | P31: операции с персональными данными - сбор | Q31: хранение | R31: накопление | S31: уточнение | T31: использование | U31: передача | V31: уничтожение данных
A32: ='данные для анализа'!A32 | B32: сбор | C32: запись | D32: систематизация | E32: накопление | F32: хранение | G32: уточнение (обновление, изменени) | H32: извлечение | I32: использование | J32: передача (распространение, предоставление, доступ) | K32: блокирование | L32: удаление | M32: уничтожение персональных данных
A33: ='данные для анализа'!A33 | B33: сбор | C33: запись | D33: систематизация | E33: накопление | F33: хранение | G33: уточнение (обновление, изменение) | H33: извлечение | I33: использование | J33: передача (распространение, предоставление, доступ) | K33: обезличивание | L33: блокирование | M33: удаление | N33: уничтожение персональных данных
A34: ='данные для анализа'!A34 | B34: смешанная обработка персональных данных с передачей информации по внутренней защищенной локальной сети университета без выхода во внешние сети | C34: передача деперсонализированных общедоступных данных в открытые системы: государственные организации по сбору статистики | D34: вышестоящие федеральные организации | E34: передача данных в организации: банки | F34: налоговая служба | G34: пенсионный фонд | H34: казначейство | I34: государственные организации по сбору статистики | J34: вышестоящие федеральные организации
A35: ='данные для анализа'!A35 | B35: осуществляется смешанная обработка персональных данных
A36: ='данные для анализа'!A36 | B36: сбор | C36: систематизация | D36: накопление | E36: хранение | F36: уточнение (обновление, изменение) | G36: использование | H36: распространение | I36: обезличивание | J36: блокирование | K36: уничтожение
A37: ='данные для анализа'!A37 | B37: сбор | C37: запись | D37: систематизация | E37: накопление | F37: хранение | G37: уточнение | H37: (обновление, изменение) | I37: извлечение | J37: использование | K37: передача (предоставление) | L37: блокирование | M37: удаление | N37: уничтожение обработка персональных данных будет осуществляться путем смешанной обработки
A38: ='данные для анализа'!A38 | B38: сбор | C38: запись | D38: систематизация | E38: накопление | F38: хранение | G38: уточнение (обновление, изменение) | H38: извлечение | I38: использование | J38: передача (распространение, предоставление, доступ) | K38: обезличивание | L38: блокирование | M38: удаление | N38: уничтожение
A39: ='данные для анализа'!A39 | B39: сбор | C39: запись | D39: систематизация | E39: накопление | F39: хранение | G39: уточнение (обновление,изменение) | H39: извлечение | I39: использование | J39: передача (распространение, предоставление, доступ) | K39: обезличивание | L39: блокирование | M39: удаление уничтожение персональных данных
A40: ='данные для анализа'!A40 | B40: сбор | C40: запись | D40: систематизация | E40: накопление | F40: хранение | G40: уточнение (обновление, изменение) | H40: извлечение | I40: использование | J40: передача (распространение, предоставление, доступ) | K40: обезличивание | L40: блокирование | M40: удаление | N40: уничтожение персональных данных
A41: ='данные для анализа'!A41 | B41: обработка: прием | C41: сбор | D41: запись | E41: систематизация | F41: накопление | G41: использование | H41: хранение | I41: уточнение (изменение, обновление) | J41: передача (распространение, предоставление, доступ) | K41: извлечение | L41: уничтожение | M41: блокирование | N41: обезличивание
A42: ='данные для анализа'!A42 | B42: сбор | C42: накопление | D42: хранение | E42: уточнение (обновление, изменение) | F42: использование | G42: уничтожение персональных данных
A43: ='данные для анализа'!A43 | B43: сбор | C43: систематизация | D43: накопление | E43: хранение | F43: уточнение (обновление, изменение) | G43: использование | H43: обезличивание | I43: блокирование | J43: уничтожение персональных данных
A44: ='данные для анализа'!A44 | B44: сбор | C44: запись | D44: систематизация | E44: накопление | F44: хранение | G44: уточнение (обновление, изменение) | H44: извлечение | I44: использование | J44: передача (распространение, предоставление, доступ) | K44: обезличивание | L44: блокирование | M44: удаление | N44: уничтожение персональных данных
A45: ='данные для анализа'!A45 | B45: cбор | C45: систематизация | D45: накопление | E45: хранение | F45: уточнение (обновление, изменение) | G45: использование | H45: распространение (в тч передача) | I45: обезличивание | J45: блокирование | K45: уничтожение персональных данных
A46: ='данные для анализа'!A46 | B46: сбор | C46: запись | D46: систематизация | E46: накопление | F46: хранение | G46: уточнение (обновление, изменение) | H46: извлечение | I46: использование | J46: передача (распространение, предоставление, доступа) | K46: обезличивание | L46: блокирование | M46: удаление | N46: уничтожение персональных данных
A47: ='данные для анализа'!A47 | B47: сбор | C47: систематизация | D47: накопление | E47: хранение | F47: уточнение (обновление, изменение) | G47: ис-пользование | H47: передача в территориальные органы фонда обязательного медицинского стра-хования | I47: территориальные органы фонда социального страхования рф | J47: территориальные органы пенсионного фонда российской федерации | K47: территориальные органы фнс россии | L47: региональные отделения сбербанка россии | M47: военные комиссариаты
A48: ='данные для анализа'!A48 | B48: сбор | C48: запись | D48: систематизация | E48: накопление | F48: хранение | G48: уточнение | H48: (обновление, изменение) | I48: извлечение | J48: использование | K48: передача (распространение, предоставление, доступ) | L48: блокирование | M48: удаление | N48: уничтожение
A49: ='данные для анализа'!A49 | B49: применяется смешанная обработка персональных данных
A50: ='данные для анализа'!A50 | B50: сбора | C50: обработки | D50: систематизации | E50: хранения
A51: ='данные для анализа'!A51 | B51: сбор | C51: запись | D51: систематизация | E51: накопление | F51: хранение | G51: уточнение (обновление, изменение) | H51: извле-чение | I51: использование | J51: передача (распространение, предоставление, доступ) | K51: обезличивание | L51: бло-кирование | M51: удаление | N51: уничтожение персональных данных
A52: ='данные для анализа'!A52 | B52: сбор | C52: запись | D52: систематизация | E52: накопление | F52: хранение | G52: уточнение (обновление, изменение) | H52: извлечение | I52: использование | J52: передачу (распространение, предоставление, доступ) | K52: блокирование | L52: удаление | M52: уничтожение персональных данных
A53: ='данные для анализа'!A53 | B53: сбор | C53: запись | D53: систематизацию | E53: накопление | F53: хранение | G53: уточнение (обновление, изменение) | H53: извлечение | I53: использование | J53: передачу (предоставление, доступ) | K53: обезличивание | L53: блокирование | M53: удаление | N53: уничтожение такие действия как использование | O53: уточнение (обновление, изменение) | P53: передача | Q53: обезличивание | R53: блокирование | S53: уничтожение осуществляются с использованием персонального компьютера при непосредственном участии человека
A54: ='данные для анализа'!A54 | B54: сбор | C54: систематизация | D54: накопление | E54: хранение | F54: уточнение (обновление, изменение) | G54: использование | H54: распространение (в том числе передача) | I54: блокирование | J54: уничтожение персональных данных
A55: ='данные для анализа'!A55 | B55: сбор | C55: систематизация | D55: накопление | E55: хранение | F55: уточнение | G55: копирование | H55: удаление | I55: обновление | J55: изменение | K55: использование | L55: распространение (передача) | M55: обезличивание | N55: блокирование | O55: уничтожение | P55: извлечение
A56: ='данные для анализа'!A56 | B56: сбор | C56: хранение | D56: уточнение | E56: передача
A57: ='данные для анализа'!A57 | B57: сбор | C57: запись | D57: систематизацию | E57: накопление | F57: хранение | G57: уточнение (обновление, изменение) | H57: извлечение | I57: использование | J57: передачу (распространение, предоставление, доступ) | K57: обезличивание | L57: блокирование | M57: удаление | N57: уничтожение | O57: персональных данных
A58: ='данные для анализа'!A58 | B58: сбор | C58: систематизация | D58: накопление | E58: хранение | F58: уточнение (обновление, изменение) | G58: использование | H58: распространение (в том числе передача) | I58: обезличивание | J58: блокирование | K58: уничтожение
A59: ='данные для анализа'!A59 | B59: ведение трудовых книжек | C59: _xd_ ведение личных дел на работников университета | D59: _xd_ ведение личных дел студентов университета | E59: _xd_ учет и хранение договоров | F59: заключенных с физическими лицами: заказчиками и потребителями | G59: _xd_ учет и хранение государственных контрактов на оказание преподавательских услуг
A60: ='данные для анализа'!A60 | B60: сбор | C60: систематизация | D60: накопление | E60: хранение | F60: обновление | G60: изменение | H60: использование | I60: обезличивание | J60: блокирование | K60: уничтожение | L60: в том числе посредством внесения их в электронную базу данных | M60: включения в списки (реестры) и отчетные формы | N60: предусмотренные документами | O60: регламентирующими предоставление отчетных данных (документов) передаваемых по локальной сети юридического лица и по сети интернет в части сдачи налоговой и бухгалтерской отчетности и начисления взносов на обязательное пенсионное страхование
A61: ='данные для анализа'!A61 | B61: сбор | C61: систематизация | D61: накопление | E61: хранение | F61: уточнение (обновление, изменение) | G61: _xd_ использование | H61: распространение (в том числе передача) | I61: обезличивание | J61: блокирование | K61: _xd_ уничтожение персональных данных
A62: ='данные для анализа'!A62 | B62: сбор | C62: систематизация | D62: накопление | E62: хранение | F62: уточнение (обновление, изменение) | G62: использование | H62: передача (распространение, предоставление, доступ) | I62: обезличивание | J62: блокирование | K62: удаление | L62: уничтожение
A63: ='данные для анализа'!A63 | B63: путем: смешанной обработки персональных данных информация передается по внутренней сети организации | C63: доступ к информации имеет ограниченный круг должностных лиц
A64: ='данные для анализа'!A64 | B64: неавтоматизированная обработка-ведение трудовых книжек | C64: личных дел | D64: журналов | E64: отчётов | F64: анкет | G64: заявлений договоров | H64: автоматизированная обработка - внесение в испдн: «корпоративная информационная система башгу» | I64: «сайт» башгу | J64: «скуд башгу» | K64: операции с персональными данными: сбор | L64: запись | M64: систематизация | N64: накопление | O64: хранение | P64: уточнение (обновление, изменение) | Q64: извлечение | R64: использование | S64: передачу | T64: обезличивание | U64: блокирование | V64: удаление | W64: уничтожение
A65: ='данные для анализа'!A65 | B65: сбор | C65: систематизация | D65: накопление | E65: хранение | F65: уточнение (обновление, изменение) | G65: использование | H65: распространение (в т ч передача) | I65: уничтожение
A66: ='данные для анализа'!A66 | B66: сбор | C66: запись | D66: систематизация | E66: накопление | F66: хранение | G66: уточнение (обновление, изменение) | H66: извлечение | I66: использования | J66: передача (распространение, предоставление, доступ) | K66: обезличивание | L66: блокирование | M66: удаление | N66: уничтожение
A67: ='данные для анализа'!A67 | B67: смешанная обработка данных с передачей информации по линиям связи
A68: ='данные для анализа'!A68 | B68: сбор | C68: хранение | D68: обновление
A69: ='данные для анализа'!A69 | B69: сбор | C69: запись | D69: систематизация | E69: накопление | F69: хранение | G69: уточнение (обновление, изменение) | H69: извлечение | I69: использование | J69: передача (распространение, предоставление, доступ) | K69: блокирование | L69: удаление | M69: уничтожение персональных данных
A70: ='данные для анализа'!A70 | B70: смешанная | C70: с передачей по внутренней сети юридического лица | D70: без передачи по сети_xd_ интернет
A71: ='данные для анализа'!A71 | B71: ведения трудовых книжек | C71: личных дел работников и обучающихся | D71: внесения информации в информационные системы департамента образования города москвы и общегородские информационные системы | E71: хранения | F71: систематизации | G71: уточнения | H71: блокирования | I71: уничтожения персональных данных | J71: передачи персональных данных третьим лицам только на основании федеральных законов | K71: устанавливающих цель | L71: условия получения персональных данных и круг субъектов персональных данных | M71: обеспечения предоставления социального пакета
A72: ='данные для анализа'!A72 | B72: фгбоу впо "агу" осуществляет следующие действия | C72: совершаемые с персональными данными | D72: включая сбор | E72: запись | F72: систематизацию | G72: накопление | H72: хранение | I72: уточнение (обновление, изменение) | J72: извлечение | K72: использование | L72: передачу (распространение, предоставление, доступ) | M72: обезличивание | N72: блокирование | O72: удаление | P72: уничтожение | Q72: персональных данных
A73: ='данные для анализа'!A73 | B73: сбор | C73: систематизация | D73: накопление | E73: хранение | F73: уточнение (обновление, изменение) | G73: использование | H73: передача | I73: уничтожение
A74: ='данные для анализа'!A74 | B74: Смешанная обработка
A75: ='данные для анализа'!A75 | B75: сбор | C75: систематизация | D75: накопление | E75: хранение | F75: уточнение (обновление, изменение) | G75: использование | H75: распространение (в том числе передача) | I75: обезличивание | J75: блокирование и уничтожение
A76: ='данные для анализа'!A76 | B76: регистрация данных
A77: ='данные для анализа'!A77 | B77: сбор | C77: запись | D77: систематизация | E77: накопление | F77: хранение | G77: уточнение (изменение, обновление) | H77: использование | I77: передача | J77: обезличивание | K77: блокирование | L77: удаление | M77: уничтожение
A78: ='данные для анализа'!A78 | B78: обработка вышеуказанных персональных данных будет осуществляться путем: сбора | C78: записи | D78: систематизации | E78: накопления | F78: хранения | G78: уточнения (обновления, изменения) | H78: извлечения | I78: использования | J78: передачи (распространения, предоставления, доступа) | K78: обезличивания | L78: блокировки | M78: удаления | N78: уничтожения персональных данных
A79: ='данные для анализа'!A79 | B79: неавтоматизированная обработка - ведение трудовых книжек | C79: личных дел | D79: журналов | E79: отчётов | F79: договоров | G79: автоматизированная обработка - внесение персональных данных в информационную систему испдн угнту | H79: операции с персональными данными: сбор | I79: запись | J79: систематизация | K79: накопление | L79: хранение | M79: уточнение (обновление, изменение!, извлечение, использование, передача /предоставление, доступ!, блокирование, удаление, уничтожение персональных данных
A80: ='данные для анализа'!A80 | B80: сбор | C80: запись | D80: систематизацию | E80: накопление | F80: хранение | G80: уточнение (обновление, изменение) | H80: извлечение | I80: использование | J80: передачу (распространение, предоставление, доступ) | K80: обезличивание | L80: блокирование | M80: удаление | N80: уничтожение
A81: ='данные для анализа'!A81 | B81: сбор | C81: запись | D81: систематизация | E81: накопление | F81: хранение | G81: уточнение (обновление, изменение) | H81: извлечение | I81: использование | J81: передача (распространение, предоставление, доступ) | K81: обезличивание | L81: блокирование | M81: удаление | N81: уничтожение
A82: ='данные для анализа'!A82 | B82: сбор | C82: анализ | D82: обобщение | E82: хранение | F82: изменение | G82: дополнение | H82: передача | I82: уничтожение
A83: ='данные для анализа'!A83 | B83: сбор | C83: запись | D83: накопление | E83: хранение | F83: обновление | G83: изменения
A84: ='данные для анализа'!A84 | B84: обработка вышеуказанных персональных данных будет осуществляться путем сбора | C84: записи | D84: систематизации | E84: накопления | F84: хранения | G84: уточнения (обновления, изменения) | H84: извлечения | I84: использования | J84: передачи (распространения, предоставления, доступа) | K84: обезличивания | L84: блокирования | M84: удаления | N84: уничтожения персональных данных
A85: ='данные для анализа'!A85 | B85: обработка вышеуказанных персональных данных будет осуществляться путем: смешанная обработка персональных данных с передачей информации по внутренним защищенным локальным сетям юргпу(нпи) без выхода во внешние сети | C85: неавтоматизированная обработка персональных данных | D85: смешанная обработка общедоступных персональных данных | E85: передача деперсонализированных общедоступных данных в открытые системы | F85: передача деперсонализированных статистических данных в открытые системы: государственные организации по сбору статистики | G85: вышестоящие федеральные организации | H85: передача данных в организации: банки | I85: налоговая служба | J85: пенсионный фонд | K85: казначейство | L85: государственные организации по сбору статистики | M85: вышестоящие федеральные организации университет при обработке персональных данных принимает все необходимые правовые | N85: организационные и технические меры для их защиты от неправомерного или случайного доступа | O85: уничтожения | P85: изменения | Q85: блокирования | R85: копирования | S85: предоставления | T85: распространения | U85: а также от иных неправомерных действий в отношении них
A86: ='данные для анализа'!A86 | B86: сбор | C86: систематизация | D86: накопление | E86: хранение | F86: уточнение (обновление, изменение) | G86: использование | H86: распространение (в том числе передача) | I86: обезличивание | J86: блокирование | K86: уничтожение персональных данных
A87: ='данные для анализа'!A87 | B87: осуществляется путем: сбора | C87: записи | D87: систематизации | E87: накопления | F87: хранения | G87: уточнения (обновления, изменения) | H87: использования | I87: передачи (распространения, предоставления, доступа) | J87: обезличивания | K87: блокирования | L87: удаления | M87: уничтожения персональных данных
A88: ='данные для анализа'!A88 | B88: осуществляется путем: сбора | C88: записи | D88: систематизации | E88: накопления | F88: хранения | G88: уточнения (обновления, изменения) | H88: использования | I88: передачи (распространения, предоставления, доступа) | J88: обезличивания | K88: блокирования | L88: удаления | M88: уничтожения персональных данных
A89: ='данные для анализа'!A89 | B89: автоматизировано с использованием биллинговой системы bg billing | C89: автоматизированных систем (внутренние системы хранения "с: бухгалтерия государственных учреждений", "с: университет", "с: камин заработная плата") данные включают сбор | D89: запись | E89: систематизацию | F89: накопление | G89: хранение | H89: уточнение | I89: извлечение | J89: использование | K89: удаление | L89: уничтожение персональных данных и доступны только ряду ответственных сотрудников неавтоматизированная обработка включает в себя работу с договорами | M89: трудовыми книжками | N89: бумажной картотекой сотрудников и студентов
A90: ='данные для анализа'!A90 | B90: сбор | C90: запись | D90: систематизация | E90: накопление | F90: хранение | G90: уточнение (обновление, изменение) | H90: извлечение | I90: использование | J90: передача (распространение, предоставление, доступ) | K90: обезличивание | L90: блокирование | M90: удаление | N90: уничтожение
A91: ='данные для анализа'!A91 | B91: сбор | C91: запись | D91: хранение | E91: уточнение (обновление, изменение) | F91: использование | G91: передача (предоставление) | H91: удаление
A92: ='данные для анализа'!A92 | B92: сбор | C92: систематизация | D92: накопление | E92: хранение | F92: уточнение (обновление, изменение) | G92: использование | H92: передача | I92: уничтожение смешанная обработка вышеуказанных персональных данных осуществляется с использованием автоматизированных систем обработки данных | J92: с передачей полученной информации по внутренней локальной вычислительной сети и с использованием сети интернет
A93: ='данные для анализа'!A93 | B93: обработка вышеуказанных персональных данных будет осуществляться путем смешанной обработки персональных данных с передачей полученной в ходе обработки персональных данных информации по внутренней сети нияу мифи (информация доступна лишь для строго определенных сотрудников юридического лица) | C93: в тч с использованием сети общего пользования
A94: ='данные для анализа'!A94 | B94: сбор | C94: систематизация | D94: накопление | E94: хранение | F94: уточнение (обновление, изменение использования, распространение) | G94: в том числе передача), обезличивание, блокирование, уничтожение персональных данных)
A95: ='данные для анализа'!A95 | B95: сбор | C95: запись | D95: систематизация | E95: накопление | F95: хранение | G95: уточнение (обновление, изменение) | H95: извлечение | I95: использование | J95: передача (распространение, предоставление, доступ) | K95: обезличивание | L95: блокирование | M95: удаление | N95: уничтожение
A96: ='данные для анализа'!A96 | B96: сбор | C96: накопление | D96: хранение | E96: уточнение (обновление, изменение) | F96: систематизация | G96: использование | H96: распространение (в том числе передача) | I96: обезличивание | J96: блокирование | K96: уничтожение персональных данных | L96: необходимых для ведения образовательной и административно-хозяйственной деятельности обмен (прием, передача) персональными данными между аггпу им вм шукшина и третьими лицами (организациями) в соответствии с заключенными между ними договорами и соглашениями | M96: в целях соблюдения законных прав и интересов субъекта персональных данных
A97: ='данные для анализа'!A97 | B97: сбор | C97: запись | D97: систематизация | E97: накопление | F97: хранение | G97: уточнение (обновление, изменение) | H97: извлечение | I97: использование | J97: передача (распространение, предоставление, доступ) | K97: обезличивание | L97: блокирование | M97: удаление | N97: уничтожение персональных данных
A98: ='данные для анализа'!A98 | B98: сбор | C98: запись | D98: систематизация | E98: накопление | F98: хранение | G98: уточнение (обновление, изменение) | H98: извлечение | I98: использование | J98: передача (в том числе трансграничная) | K98: доступ и предоставление указанным в настоящем согласии организациям | L98: обезличивание | M98: блокирование | N98: удаление | O98: уничтожение
A99: ='данные для анализа'!A99 | B99: неавтоматизированная обработка - ведение трудовых книжек | C99: личных дел | D99: журналов | E99: отчётов | F99: договоров | G99: автоматизированная обработка - внесение персональных данных в информационные системы c | H99: пфр | I99: скуд | J99: спринт | K99: деканат | L99: операции с персональными данными: сбор | M99: хранение | N99: накопление | O99: уточнение | P99: передача | Q99: уничтожение данных
A100: ='данные для анализа'!A100 | B100: сбора | C100: записи | D100: систематизации | E100: накопления | F100: хранения | G100: уточнения (обновления, изменения) | H100: извлечения | I100: использования | J100: передачи (распространения, предоставления, доступа) | K100: блокирования | L100: удаления | M100: уничтожения персональных данных
...

Sheet разбиение по частям (лемматиз)
A1: данные | B1: слово 1 | C1: слово 2 | D1: слово 3 | E1: слово 4 | F1: слово 5 | G1: слово 6 | H1: слово 7 | I1: слово 8 | J1: слово 9 | K1: слово 10 | L1: слово 11 | M1: слово 12 | N1: слово 13 | O1: слово 14 | P1: слово 15 | Q1: слово 16 | R1: слово 17 | S1: слово 18 | T1: слово 19 | U1: слово 20 | V1: слово 21
A2: ='данные для анализа'!A2 | B2: сбор | C2: систематизация | D2: хранение | E2: использование | F2: уточнение | G2: обновление | H2: изменение | I2: накопление | J2: обезличивание | K2: блокирование | L2: уничтожение | M2: передача | N2: казначейство | O2: банк | P2: налоговый | Q2: служба | R2: федеральный | S2: фонд
A3: ='данные для анализа'!A3 | B3: сбор | C3: систематизация | D3: накопление | E3: хранение | F3: уточнение | G3: обновление | H3: изменение | I3: использование | J3: распространение | K3: число | L3: передача | M3: уничтожение | N3: персональный | O3: данные
A4: ='данные для анализа'!A4 | B4: сбор | C4: запись | D4: систематизация | E4: накопление | F4: хранение | G4: уточнение | H4: обновление | I4: изменение | J4: извлечение | K4: использование | L4: передача | M4: распространение | N4: предоставление | O4: доступ | P4: обезличивание | Q4: блокирование | R4: удаление | S4: уничтожение | T4: персональный | U4: данные
A5: ='данные для анализа'!A5 | B5: путем | C5: смешать | D5: обработка | E5: персональный | F5: данные | G5: передача | H5: информация | I5: внутренний | J5: сеть
A6: ='данные для анализа'!A6 | B6: сбор | C6: систематизация | D6: накопление | E6: хранение | F6: уточнение | G6: распространение | H6: обезличивание | I6: уничтожение
A7: ='данные для анализа'!A7 | B7: смешать | C7: обработка | D7: вышеуказанный | E7: персональный | F7: данные | G7: быть | H7: осуществляться | I7: использование | J7: пэвм | K7: информация | L7: доступный | M7: лишь | N7: строго | O7: определенный | P7: сотрудник | Q7: юридический | R7: лицо | S7: передача | T7: получать | U7: информация | V7: локальный | W7: сеть
A8: ='данные для анализа'!A8 | B8: формирование | C8: документация | D8: необходимый | E8: осуществление | F8: образовательный | G8: научный | H8: деятельность
A9: ='данные для анализа'!A9 | B9: сбор | C9: запись | D9: систематизация | E9: накопление | F9: хранение | G9: уточнение | H9: обновление | I9: изменение | J9: извлечение | K9: использование | L9: передача | M9: распространение | N9: предоставление | O9: блокирование | P9: трансграничный | Q9: передача | R9: удаление | S9: уничтожение | T9: персональный | U9: данные
A10: ='данные для анализа'!A10 | B10: сбор | C10: запись | D10: систематизация | E10: накопление | F10: хранение | G10: уточнение | H10: обновление | I10: изменение | J10: извлечение | K10: использование | L10: передача | M10: распространение | N10: предоставление | O10: доступ | P10: обезличивание | Q10: блокирование | R10: удаление | S10: уничтожение | T10: персональный | U10: данные
A11: ='данные для анализа'!A11 | B11: сбор | C11: систематизация | D11: накопление | E11: хранение | F11: уточнение | G11: использование | H11: распространение | I11: блокирование | J11: уничтожение
A12: ='данные для анализа'!A12 | B12: сбор | C12: запись | D12: систематизация | E12: накопление | F12: хранение | G12: уточнение | H12: обновление | I12: изменение | J12: извлечение | K12: использование | L12: передача | M12: распространение | N12: предоставление | O12: доступ | P12: обезличивание | Q12: блокирование | R12: удаление | S12: уничтожение
A13: ='данные для анализа'!A13 | B13: смешать | C13: обработка
A14: ='данные для анализа'!A14 | B14: смешать | C14: обработка | D14: использование | E14: пэвм | F14: информация | G14: доступный | H14: лишь | I14: строго | J14: определенный | K14: сотрудник | L14: юридический | M14: лицо | N14: передача | O14: получать | P14: информация | Q14: использование | R14: сеть | S14: общий | T14: пользование | U14: интернет
A15: ='данные для анализа'!A15 | B15: смешать | C15: обработка | D15: использование | E15: передача | F15: получать | G15: информация | H15: использование | I15: сеть | J15: общий | K15: пользование | L15: интернет
A16: ='данные для анализа'!A16 | B16: смешать | C16: обработка | D16: вышеуказанный | E16: персональный | F16: данные | G16: быть | H16: осуществляться | I16: использование | J16: пэвм | K16: информация | L16: доступный | M16: лишь | N16: строго | O16: определенный | P16: сотрудник | Q16: юридический | R16: лицо | S16: передача | T16: получать | U16: информация | V16: использование | W16: сеть | X16: общий | Y16: пользование | Z16: интернет
A17: ='данные для анализа'!A17 | B17: смешать | C17: обработка | D17: использование | E17: бумажный | F17: носитель | G17: передача | H17: получать | I17: информация | J17: внутренний | K17: сеть | L17: учреждение | M17: сеть | N17: общий | O17: пользование | P17: интернет
A18: ='данные для анализа'!A18 | B18: сбор | C18: запись | D18: систематизация | E18: накопление | F18: хранение | G18: уточнение | H18: обновление | I18: изменение | J18: извлечение | K18: использование | L18: передача | M18: распространение | N18: предоставление | O18: доступ | P18: обезличивание | Q18: блокирование | R18: удаление | S18: уничтожение
A19: ='данные для анализа'!A19 | B19: смешать | C19: обработка | D19: персональный | E19: данные | F19: передача | G19: данные | H19: использование | I19: закрытый | J19: россия | K19: работа | L19: данные | M19: категорированный | N19: компьютерный | O19: рабочий | P19: место | Q19: работа
A20: ='данные для анализа'!A20 | B20: сбор | C20: систематизация | D20: накопление | E20: хранение | F20: уточнение | G20: обновление | H20: изменение | I20: использование | J20: число | K20: передача | L20: обезличивание | M20: блокирование | N20: уничтожение | O20: быть | P20: осуществляться | Q20: учет | R20: действующий | S20: законодательство
A21: ='данные для анализа'!A21 | B21: прием | C21: сбор | D21: систематизация | E21: накопление | F21: использование | G21: хранение | H21: уточнение | I21: обновление | J21: изменение | K21: распространение | L21: число | M21: передача | N21: уничтожение | O21: блокирование | P21: обезличивание
A22: ='данные для анализа'!A22 | B22: сбор | C22: запись | D22: систематизация | E22: накопление | F22: хранение | G22: уточнение | H22: использование | I22: обезличивание | J22: удаление | K22: уничтожение
A23: ='данные для анализа'!A23 | B23: сбор | C23: систематизация | D23: накопление | E23: хранение | F23: уточнение | G23: обновление | H23: изменение | I23: использование | J23: распространение | K23: передача | L23: уничтожение
A24: ='данные для анализа'!A24 | B24: сбор | C24: запись | D24: систематизация | E24: накопление | F24: хранение | G24: уточнение | H24: обновление | I24: изменение | J24: извлечение | K24: использование | L24: передача | M24: распространение | N24: предоставление | O24: доступ | P24: обезличивание | Q24: блокирование | R24: удаление | S24: уничтожение
A25: ='данные для анализа'!A25 | B25: обработка | C25: персональный | D25: данные | E25: осуществляться | F25: путем | G25: смешанный | H25: обработка | I25: персональный | J25: данные | K25: информация | L25: получать | M25: обработка | N25: персональный | O25: данные | P25: передаваться | Q25: внутренний | R25: локальный | S25: информационный | T25: сеть | U25: юридический | V25: лицо | W25: который | X25: доступный | Y25: строго | Z25: определенный | AA25: должностной | AB25: лицо | AC25: спбгуэфа | AD25: соответствие | AE25: приказ | AF25: ректор
A26: ='данные для анализа'!A26 | B26: сбор | C26: запись | D26: систематизация | E26: накопление | F26: хранение | G26: уточнение | H26: обновление | I26: изменение | J26: извлечение | K26: использование | L26: передача | M26: распространение | N26: предоставление | O26: доступ | P26: блокирование | Q26: удаление | R26: уничтожение
A27: ='данные для анализа'!A27 | B27: сбор | C27: запись | D27: систематизация | E27: накопление | F27: хранение | G27: уточнение | H27: обновление | I27: изменение | J27: извлечение | K27: использование | L27: передача | M27: распространение | N27: предоставление | O27: доступ | P27: обезличивание | Q27: блокирование | R27: удаление | S27: уничтожение | T27: персональный | U27: данные
A28: ='данные для анализа'!A28 | B28: сбор | C28: систематизация | D28: накопление | E28: хранение | F28: уточнение | G28: обновление | H28: изменение | I28: использование | J28: распространение | K28: число | L28: передача | M28: уничтожение
A29: ='данные для анализа'!A29 | B29: смешать | C29: обработка
A30: ='данные для анализа'!A30 | B30: обработка | C30: персональный | D30: данные | E30: осуществляться | F30: путем | G30: смешанный | H30: обработка | I30: включать | J30: сбор | K30: систематизация | L30: накопление | M30: хранение | N30: уточнение | O30: использование | P30: передача | Q30: информация | R30: внутренний | S30: сеть | T30: двгту | U30: специально | V30: выделять | W30: помещение | X30: использование | Y30: программный | Z30: средство | AA30: аутентификация | AB30: авторизация | AC30: пользователь | AD30: включать | AE30: список | AF30: лицо | AG30: допускать | AH30: обработка | AI30: персональный | AJ30: данные
A31: ='данные для анализа'!A31 | B31: неавтоматизированный | C31: обработка | D31: ведение | E31: трудовой | F31: книжка | G31: личный | H31: дело | I31: договор | J31: список | K31: сотрудник | L31: обучающийся | M31: картотека | N31: сведение | O31: сотрудник | P31: картотека | Q31: сведение | R31: студент | S31: журнал | T31: учебный | U31: группа | V31: автоматизированный | W31: обработка | X31: внесение | Y31: персональный | Z31: данные | AA31: работник | AB31: информационный | AC31: система | AD31: система | AE31: организация | AF31: приемная | AG31: компания | AH31: модус | AI31: подсистема | AJ31: абитуриент | AK31: автоматизированный | AL31: информационный | AM31: библиотечный | AN31: система | AO31: марк | AP31: автоматизированный | AQ31: система | AR31: документооборот | AS31: дело | AT31: предприятие | AU31: система | AV31: расчет | AW31: начисление | AX31: зарплата | AY31: сотрудник | AZ31: амба | BA31: система | BB31: расчет | BC31: стипендия | BD31: амба | BE31: система | BF31: ведение | BG31: кадровый | BH31: учет | BI31: расчет | BJ31: зарплата | BK31: контур | BL31: персонал | BM31: автоматизированный | BN31: система | BO31: бухгалтерский | BP31: учет | BQ31: бюджетный | BR31: учреждение | BS31: парус | BT31: бухгалтерия | BU31: операция | BV31: персональный | BW31: данные | BX31: сбор | BY31: хранение | BZ31: накопление | CA31: уточнение | CB31: использование | CC31: передача | CD31: уничтожение | CE31: данный
A32: ='данные для анализа'!A32 | B32: сбор | C32: запись | D32: систематизация | E32: накопление | F32: хранение | G32: уточнение | H32: обновление | I32: изменень | J32: извлечение | K32: использование | L32: передача | M32: распространение | N32: предоставление | O32: доступ | P32: блокирование | Q32: удаление | R32: уничтожение | S32: персональный | T32: данные
A33: ='данные для анализа'!A33 | B33: сбор | C33: запись | D33: систематизация | E33: накопление | F33: хранение | G33: уточнение | H33: обновление | I33: изменение | J33: извлечение | K33: использование | L33: передача | M33: распространение | N33: предоставление | O33: доступ | P33: обезличивание | Q33: блокирование | R33: удаление | S33: уничтожение | T33: персональный | U33: данные
A34: ='данные для анализа'!A34 | B34: смешать | C34: обработка | D34: персональный | E34: данные | F34: передача | G34: информация | H34: внутренний | I34: защищать | J34: локальный | K34: сеть | L34: университет | M34: выход | N34: внешний | O34: сеть | P34: передача | Q34: деперсонализировать | R34: общедоступный | S34: данные | T34: открытый | U34: система | V34: государственный | W34: организация | X34: сбор | Y34: статистика | Z34: вышестоящий | AA34: федеральный | AB34: организация | AC34: передача | AD34: данные | AE34: организация | AF34: банка | AG34: налоговый | AH34: служба | AI34: пенсионный | AJ34: фонд | AK34: казначейство | AL34: государственный | AM34: организация | AN34: сбор | AO34: статистика | AP34: вышестоящий | AQ34: федеральный | AR34: организация
A35: ='данные для анализа'!A35 | B35: осуществляться | C35: смешать | D35: обработка | E35: персональный | F35: данный
A36: ='данные для анализа'!A36 | B36: сбор | C36: систематизация | D36: накопление | E36: хранение | F36: уточнение | G36: обновление | H36: изменение | I36: использование | J36: распространение | K36: обезличивание | L36: блокирование | M36: уничтожение
A37: ='данные для анализа'!A37 | B37: сбор | C37: запись | D37: систематизация | E37: накопление | F37: хранение | G37: уточнение | H37: обновление | I37: изменение | J37: извлечение | K37: использование | L37: передача | M37: предоставление | N37: блокирование | O37: удаление | P37: уничтожение | Q37: обработка | R37: персональный | S37: данные | T37: быть | U37: осуществляться | V37: путем | W37: смешанный | X37: обработка
A38: ='данные для анализа'!A38 | B38: сбор | C38: запись | D38: систематизация | E38: накопление | F38: хранение | G38: уточнение | H38: обновление | I38: изменение | J38: извлечение | K38: использование | L38: передача | M38: распространение | N38: предоставление | O38: доступ | P38: обезличивание | Q38: блокирование | R38: удаление | S38: уничтожение
A39: ='данные для анализа'!A39 | B39: сбор | C39: запись | D39: систематизация | E39: накопление | F39: хранение | G39: уточнение | H39: обновление | I39: изменение | J39: извлечение | K39: использование | L39: передача | M39: распространение | N39: предоставление | O39: доступ | P39: обезличивание | Q39: блокирование | R39: удаление | S39: уничтожение | T39: персональный | U39: данные
A40: ='данные для анализа'!A40 | B40: сбор | C40: запись | D40: систематизация | E40: накопление | F40: хранение | G40: уточнение | H40: обновление | I40: изменение | J40: извлечение | K40: использование | L40: передача | M40: распространение | N40: предоставление | O40: доступ | P40: обезличивание | Q40: блокирование | R40: удаление | S40: уничтожение | T40: персональный | U40: данные
A41: ='данные для анализа'!A41 | B41: обработка | C41: прием | D41: сбор | E41: запись | F41: систематизация | G41: накопление | H41: использование | I41: хранение | J41: уточнение | K41: изменение | L41: обновление | M41: передача | N41: распространение | O41: предоставление | P41: доступ | Q41: извлечение | R41: уничтожение | S41: блокирование | T41: обезличивание
A42: ='данные для анализа'!A42 | B42: сбор | C42: накопление | D42: хранение | E42: уточнение | F42: обновление | G42: изменение | H42: использование | I42: уничтожение | J42: персональный | K42: данные
A43: ='данные для анализа'!A43 | B43: сбор | C43: систематизация | D43: накопление | E43: хранение | F43: уточнение | G43: обновление | H43: изменение | I43: использование | J43: обезличивание | K43: блокирование | L43: уничтожение | M43: персональный | N43: данные
A44: ='данные для анализа'!A44 | B44: сбор | C44: запись | D44: систематизация | E44: накопление | F44: хранение | G44: уточнение | H44: обновление | I44: изменение | J44: извлечение | K44: использование | L44: передача | M44: распространение | N44: предоставление | O44: доступ | P44: обезличивание | Q44: блокирование | R44: удаление | S44: уничтожение | T44: персональный | U44: данные
A45: ='данные для анализа'!A45 | B45: сбор | C45: систематизация | D45: накопление | E45: хранение | F45: уточнение | G45: обновление | H45: изменение | I45: использование | J45: распространение | K45: передача | L45: обезличивание | M45: блокирование | N45: уничтожение | O45: персональный | P45: данные
A46: ='данные для анализа'!A46 | B46: сбор | C46: запись | D46: систематизация | E46: накопление | F46: хранение | G46: уточнение | H46: обновление | I46: изменение | J46: извлечение | K46: использование | L46: передача | M46: распространение | N46: предоставление | O46: доступ | P46: обезличивание | Q46: блокирование | R46: удаление | S46: уничтожение | T46: персональный | U46: данные
A47: ='данные для анализа'!A47 | B47: сбор | C47: систематизация | D47: накопление | E47: хранение | F47: уточнение | G47: обновление | H47: изменение | I47: пользование | J47: передача | K47: территориальный | L47: орган | M47: фонд | N47: обязательный | O47: медицинский | P47: стра | Q47: хование | R47: территориальный | S47: орган | T47: фонд | U47: социальный | V47: страхование | W47: территориальный | X47: орган | Y47: пенсионный | Z47: фонд | AA47: российский | AB47: федерация | AC47: территориальный | AD47: орган | AE47: россия | AF47: региональный | AG47: отделение | AH47: сбербанк | AI47: россия | AJ47: военный | AK47: комиссариат
A48: ='данные для анализа'!A48 | B48: сбор | C48: запись | D48: систематизация | E48: накопление | F48: хранение | G48: уточнение | H48: обновление | I48: изменение | J48: извлечение | K48: использование | L48: передача | M48: распространение | N48: предоставление | O48: доступ | P48: блокирование | Q48: удаление | R48: уничтожение
A49: ='данные для анализа'!A49 | B49: применяться | C49: смешать | D49: обработка | E49: персональный | F49: данный
A50: ='данные для анализа'!A50 | B50: сбор | C50: обработка | D50: систематизация | E50: хранение
A51: ='данные для анализа'!A51 | B51: сбор | C51: запись | D51: систематизация | E51: накопление | F51: хранение | G51: уточнение | H51: обновление | I51: изменение | J51: извле | K51: чение | L51: использование | M51: передача | N51: распространение | O51: предоставление | P51: доступ | Q51: обезличивание | R51: кирование | S51: удаление | T51: уничтожение | U51: персональный | V51: данные
A52: ='данные для анализа'!A52 | B52: сбор | C52: запись | D52: систематизация | E52: накопление | F52: хранение | G52: уточнение | H52: обновление | I52: изменение | J52: извлечение | K52: использование | L52: передача | M52: распространение | N52: предоставление | O52: доступ | P52: блокирование | Q52: удаление | R52: уничтожение | S52: персональный | T52: данные
A53: ='данные для анализа'!A53 | B53: сбор | C53: запись | D53: систематизация | E53: накопление | F53: хранение | G53: уточнение | H53: обновление | I53: изменение | J53: извлечение | K53: использование | L53: передача | M53: предоставление | N53: доступ | O53: обезличивание | P53: блокирование | Q53: удаление | R53: уничтожение | S53: такой | T53: действие | U53: использование | V53: уточнение | W53: обновление | X53: изменение | Y53: передача | Z53: обезличивание | AA53: блокирование | AB53: уничтожение | AC53: осуществляться | AD53: использование | AE53: персональный | AF53: компьютер | AG53: непосредственный | AH53: участие | AI53: человек
A54: ='данные для анализа'!A54 | B54: сбор | C54: систематизация | D54: накопление | E54: хранение | F54: уточнение | G54: обновление | H54: изменение | I54: использование | J54: распространение | K54: число | L54: передача | M54: блокирование | N54: уничтожение | O54: персональный | P54: данные
A55: ='данные для анализа'!A55 | B55: сбор | C55: систематизация | D55: накопление | E55: хранение | F55: уточнение | G55: копирование | H55: удаление | I55: обновление | J55: изменение | K55: использование | L55: распространение | M55: передача | N55: обезличивание | O55: блокирование | P55: уничтожение | Q55: извлечение
A56: ='данные для анализа'!A56 | B56: сбор | C56: хранение | D56: уточнение | E56: передача
A57: ='данные для анализа'!A57 | B57: сбор | C57: запись | D57: систематизация | E57: накопление | F57: хранение | G57: уточнение | H57: обновление | I57: изменение | J57: извлечение | K57: использование | L57: передача | M57: распространение | N57: предоставление | O57: доступ | P57: обезличивание | Q57: блокирование | R57: удаление | S57: уничтожение | T57: персональный | U57: данные
A58: ='данные для анализа'!A58 | B58: сбор | C58: систематизация | D58: накопление | E58: хранение | F58: уточнение | G58: обновление | H58: изменение | I58: использование | J58: распространение | K58: число | L58: передача | M58: обезличивание | N58: блокирование | O58: уничтожение
A59: ='данные для анализа'!A59 | B59: ведение | C59: трудовой | D59: книжка | E59: ведение | F59: личный | G59: дело | H59: работник | I59: университет | J59: ведение | K59: личный | L59: дело | M59: студент | N59: университет | O59: учет | P59: хранение | Q59: договор | R59: заключать | S59: физический | T59: лицо | U59: заказчик | V59: потребитель | W59: учет | X59: хранение | Y59: государственный | Z59: контракт | AA59: оказание | AB59: преподавательский | AC59: услуга
A60: ='данные для анализа'!A60 | B60: сбор | C60: систематизация | D60: накопление | E60: хранение | F60: обновление | G60: изменение | H60: использование | I60: обезличивание | J60: блокирование | K60: уничтожение | L60: число | M60: посредством | N60: внесение | O60: электронный | P60: база | Q60: данные | R60: включение | S60: список | T60: реестр | U60: отчетный | V60: форма | W60: предусматривать | X60: документ | Y60: регламентировать | Z60: предоставление | AA60: отчетный | AB60: данные | AC60: документ | AD60: передавать | AE60: локальный | AF60: сеть | AG60: юридический | AH60: лицо | AI60: сеть | AJ60: интернет | AK60: часть | AL60: сдача | AM60: налоговый | AN60: бухгалтерский | AO60: отчетность | AP60: начисление | AQ60: взнос | AR60: обязательный | AS60: пенсионный | AT60: страхование
A61: ='данные для анализа'!A61 | B61: сбор | C61: систематизация | D61: накопление | E61: хранение | F61: уточнение | G61: обновление | H61: изменение | I61: использование | J61: распространение | K61: число | L61: передача | M61: обезличивание | N61: блокирование | O61: уничтожение | P61: персональный | Q61: данные
A62: ='данные для анализа'!A62 | B62: сбор | C62: систематизация | D62: накопление | E62: хранение | F62: уточнение | G62: обновление | H62: изменение | I62: использование | J62: передача | K62: распространение | L62: предоставление | M62: доступ | N62: обезличивание | O62: блокирование | P62: удаление | Q62: уничтожение
A63: ='данные для анализа'!A63 | B63: путем | C63: смешанный | D63: обработка | E63: персональный | F63: данные | G63: информация | H63: передаваться | I63: внутренний | J63: сеть | K63: организация | L63: доступ | M63: информация | N63: иметь | O63: ограниченный | P63: круг | Q63: должностной | R63: лицо
A64: ='данные для анализа'!A64 | B64: неавтоматизированный | C64: обработка | D64: ведение | E64: трудовой | F64: книжка | G64: личный | H64: дело | I64: журнал | J64: отчет | K64: анкета | L64: заявление | M64: договор | N64: автоматизированный | O64: обработка | P64: внесение | Q64: испдна | R64: корпоративный | S64: информационный | T64: система | U64: башгу | V64: сайт | W64: башгу | X64: скуда | Y64: башгу | Z64: операция | AA64: персональный | AB64: данные | AC64: сбор | AD64: запись | AE64: систематизация | AF64: накопление | AG64: хранение | AH64: уточнение | AI64: обновление | AJ64: изменение | AK64: извлечение | AL64: использование | AM64: передача | AN64: обезличивание | AO64: блокирование | AP64: удаление | AQ64: уничтожение
A65: ='данные для анализа'!A65 | B65: сбор | C65: систематизация | D65: накопление | E65: хранение | F65: уточнение | G65: обновление | H65: изменение | I65: использование | J65: распространение | K65: передача | L65: уничтожение
A66: ='данные для анализа'!A66 | B66: сбор | C66: запись | D66: систематизация | E66: накопление | F66: хранение | G66: уточнение | H66: обновление | I66: изменение | J66: извлечение | K66: использование | L66: передача | M66: распространение | N66: предоставление | O66: доступ | P66: обезличивание | Q66: блокирование | R66: удаление | S66: уничтожение
A67: ='данные для анализа'!A67 | B67: смешать | C67: обработка | D67: данные | E67: передача | F67: информация | G67: линия | H67: связь
A68: ='данные для анализа'!A68 | B68: сбор | C68: хранение | D68: обновление
A69: ='данные для анализа'!A69 | B69: сбор | C69: запись | D69: систематизация | E69: накопление | F69: хранение | G69: уточнение | H69: обновление | I69: изменение | J69: извлечение | K69: использование | L69: передача | M69: распространение | N69: предоставление | O69: доступ | P69: блокирование | Q69: удаление | R69: уничтожение | S69: персональный | T69: данные
A70: ='данные для анализа'!A70 | B70: смешать | C70: передача | D70: внутренний | E70: сеть | F70: юридический | G70: лицо | H70: передача | I70: сеть | J70: интернет
A71: ='данные для анализа'!A71 | B71: ведение | C71: трудовой | D71: книжка | E71: личный | F71: дело | G71: работник | H71: обучающийся | I71: внесение | J71: информация | K71: информационный | L71: система | M71: департамент | N71: образование | O71: город | P71: москва | Q71: общегородской | R71: информационный | S71: система | T71: хранение | U71: систематизация | V71: уточнение | W71: блокирование | X71: уничтожение | Y71: персональный | Z71: данные | AA71: передача | AB71: персональный | AC71: данные | AD71: третий | AE71: лицо | AF71: только | AG71: основание | AH71: федеральный | AI71: закон | AJ71: устанавливать | AK71: цель | AL71: условие | AM71: получение | AN71: персональный | AO71: данные | AP71: круг | AQ71: субъект | AR71: персональный | AS71: данные | AT71: обеспечение | AU71: предоставление | AV71: социальный | AW71: пакет
A72: ='данные для анализа'!A72 | B72: фгбоу | C72: осуществлять | D72: следующий | E72: действие | F72: совершать | G72: персональный | H72: данные | I72: включая | J72: сбор | K72: запись | L72: систематизация | M72: накопление | N72: хранение | O72: уточнение | P72: обновление | Q72: изменение | R72: извлечение | S72: использование | T72: передача | U72: распространение | V72: предоставление | W72: доступ | X72: обезличивание | Y72: блокирование | Z72: удаление | AA72: уничтожение | AB72: персональный | AC72: данные
A73: ='данные для анализа'!A73 | B73: сбор | C73: систематизация | D73: накопление | E73: хранение | F73: уточнение | G73: обновление | H73: изменение | I73: использование | J73: передача | K73: уничтожение
A74: ='данные для анализа'!A74 | B74: смешать | C74: обработка
A75: ='данные для анализа'!A75 | B75: сбор | C75: систематизация | D75: накопление | E75: хранение | F75: уточнение | G75: обновление | H75: изменение | I75: использование | J75: распространение | K75: число | L75: передача | M75: обезличивание | N75: блокирование | O75: уничтожение
A76: ='данные для анализа'!A76 | B76: регистрация | C76: данные
A77: ='данные для анализа'!A77 | B77: сбор | C77: запись | D77: систематизация | E77: накопление | F77: хранение | G77: уточнение | H77: изменение | I77: обновление | J77: использование | K77: передача | L77: обезличивание | M77: блокирование | N77: удаление | O77: уничтожение
A78: ='данные для анализа'!A78 | B78: обработка | C78: вышеуказанный | D78: персональный | E78: данные | F78: быть | G78: осуществляться | H78: путем | I78: сбор | J78: запись | K78: систематизация | L78: накопление | M78: хранение | N78: уточнение | O78: обновление | P78: изменение | Q78: извлечение | R78: использование | S78: передача | T78: распространение | U78: предоставление | V78: доступ | W78: обезличивание | X78: блокировка | Y78: удаление | Z78: уничтожение | AA78: персональный | AB78: данные
A79: ='данные для анализа'!A79 | B79: неавтоматизированный | C79: обработка | D79: ведение | E79: трудовой | F79: книжка | G79: личный | H79: дело | I79: журнал | J79: отчет | K79: договор | L79: автоматизированный | M79: обработка | N79: внесение | O79: персональный | P79: данные | Q79: информационный | R79: система | S79: испдна | T79: угнту | U79: операция | V79: персональный | W79: данные | X79: сбор | Y79: запись | Z79: систематизация | AA79: накопление | AB79: хранение | AC79: уточнение | AD79: обновление | AE79: изменение | AF79: извлечение | AG79: использование | AH79: передача | AI79: предоставление | AJ79: доступ | AK79: блокирование | AL79: удаление | AM79: уничтожение | AN79: персональный | AO79: данные
A80: ='данные для анализа'!A80 | B80: сбор | C80: запись | D80: систематизация | E80: накопление | F80: хранение | G80: уточнение | H80: обновление | I80: изменение | J80: извлечение | K80: использование | L80: передача | M80: распространение | N80: предоставление | O80: доступ | P80: обезличивание | Q80: блокирование | R80: удаление | S80: уничтожение
A81: ='данные для анализа'!A81 | B81: сбор | C81: запись | D81: систематизация | E81: накопление | F81: хранение | G81: уточнение | H81: обновление | I81: изменение | J81: извлечение | K81: использование | L81: передача | M81: распространение | N81: предоставление | O81: доступ | P81: обезличивание | Q81: блокирование | R81: удаление | S81: уничтожение
A82: ='данные для анализа'!A82 | B82: сбор | C82: анализ | D82: обобщение | E82: хранение | F82: изменение | G82: дополнение | H82: передача | I82: уничтожение
A83: ='данные для анализа'!A83 | B83: сбор | C83: запись | D83: накопление | E83: хранение | F83: обновление | G83: изменение
A84: ='данные для анализа'!A84 | B84: обработка | C84: вышеуказанный | D84: персональный | E84: данные | F84: быть | G84: осуществляться | H84: путем | I84: сбор | J84: запись | K84: систематизация | L84: накопление | M84: хранение | N84: уточнение | O84: обновление | P84: изменение | Q84: извлечение | R84: использование | S84: передача | T84: распространение | U84: предоставление | V84: доступ | W84: обезличивание | X84: блокирование | Y84: удаление | Z84: уничтожение | AA84: персональный | AB84: данные
A85: ='данные для анализа'!A85 | B85: обработка | C85: вышеуказанный | D85: персональный | E85: данные | F85: быть | G85: осуществляться | H85: путем | I85: смешать | J85: обработка | K85: персональный | L85: данные | M85: передача | N85: информация | O85: внутренний | P85: защищать | Q85: локальный | R85: сеть | S85: юргпу | T85: выход | U85: внешний | V85: сеть | W85: неавтоматизированный | X85: обработка | Y85: персональный | Z85: данные | AA85: смешать | AB85: обработка | AC85: общедоступный | AD85: персональный | AE85: данные | AF85: передача | AG85: деперсонализировать | AH85: общедоступный | AI85: данные | AJ85: открытый | AK85: система | AL85: передача | AM85: деперсонализировать | AN85: статистический | AO85: данные | AP85: открытый | AQ85: система | AR85: государственный | AS85: организация | AT85: сбор | AU85: статистика | AV85: вышестоящий | AW85: федеральный | AX85: организация | AY85: передача | AZ85: данные | BA85: организация | BB85: банка | BC85: налоговый | BD85: служба | BE85: пенсионный | BF85: фонд | BG85: казначейство | BH85: государственный | BI85: организация | BJ85: сбор | BK85: статистика | BL85: вышестоящий | BM85: федеральный | BN85: организация | BO85: университет | BP85: обработка | BQ85: персональный | BR85: данные | BS85: принимать | BT85: весь | BU85: необходимый | BV85: правовой | BW85: организационный | BX85: технический | BY85: мера | BZ85: защита | CA85: неправомерный | CB85: случайный | CC85: доступ | CD85: уничтожение | CE85: изменение | CF85: блокирование | CG85: копирование | CH85: предоставление | CI85: распространение | CJ85: также | CK85: иной | CL85: неправомерный | CM85: действие | CN85: отношение
A86: ='данные для анализа'!A86 | B86: сбор | C86: систематизация | D86: накопление | E86: хранение | F86: уточнение | G86: обновление | H86: изменение | I86: использование | J86: распространение | K86: число | L86: передача | M86: обезличивание | N86: блокирование | O86: уничтожение | P86: персональный | Q86: данные
A87: ='данные для анализа'!A87 | B87: осуществляться | C87: путем | D87: сбор | E87: запись | F87: систематизация | G87: накопление | H87: хранение | I87: уточнение | J87: обновление | K87: изменение | L87: использование | M87: передача | N87: распространение | O87: предоставление | P87: доступ | Q87: обезличивание | R87: блокирование | S87: удаление | T87: уничтожение | U87: персональный | V87: данные
A88: ='данные для анализа'!A88 | B88: осуществляться | C88: путем | D88: сбор | E88: запись | F88: систематизация | G88: накопление | H88: хранение | I88: уточнение | J88: обновление | K88: изменение | L88: использование | M88: передача | N88: распространение | O88: предоставление | P88: доступ | Q88: обезличивание | R88: блокирование | S88: удаление | T88: уничтожение | U88: персональный | V88: данные
A89: ='данные для анализа'!A89 | B89: автоматизировать | C89: использование | D89: биллинговый | E89: система | F89: billing | G89: автоматизированный | H89: система | I89: внутренний | J89: система | K89: хранение | L89: бухгалтерия | M89: государственный | N89: учреждение | O89: ", " | P89: университет | Q89: ", " | R89: камин | S89: заработный | T89: плата | U89: данные | V89: включать | W89: сбор | X89: запись | Y89: систематизация | Z89: накопление | AA89: хранение | AB89: уточнение | AC89: извлечение | AD89: использование | AE89: удаление | AF89: уничтожение | AG89: персональный | AH89: данные | AI89: доступный | AJ89: только | AK89: ответственный | AL89: сотрудник | AM89: неавтоматизированный | AN89: обработка | AO89: включать | AP89: себя | AQ89: работа | AR89: договор | AS89: трудовой | AT89: книжка | AU89: бумажный | AV89: картотека | AW89: сотрудник | AX89: студент
A90: ='данные для анализа'!A90 | B90: сбор | C90: запись | D90: систематизация | E90: накопление | F90: хранение | G90: уточнение | H90: обновление | I90: изменение | J90: извлечение | K90: использование | L90: передача | M90: распространение | N90: предоставление | O90: доступ | P90: обезличивание | Q90: блокирование | R90: удаление | S90: уничтожение
A91: ='данные для анализа'!A91 | B91: сбор | C91: запись | D91: хранение | E91: уточнение | F91: обновление | G91: изменение | H91: использование | I91: передача | J91: предоставление | K91: удаление
A92: ='данные для анализа'!A92 | B92: сбор | C92: систематизация | D92: накопление | E92: хранение | F92: уточнение | G92: обновление | H92: изменение | I92: использование | J92: передача | K92: уничтожение | L92: смешать | M92: обработка | N92: вышеуказанный | O92: персональный | P92: данные | Q92: осуществляться | R92: использование | S92: автоматизированный | T92: система | U92: обработка | V92: данные | W92: передача | X92: получать | Y92: информация | Z92: внутренний | AA92: локальный | AB92: вычислительный | AC92: сеть | AD92: использование | AE92: сеть | AF92: интернет
A93: ='данные для анализа'!A93 | B93: обработка | C93: вышеуказанный | D93: персональный | E93: данные | F93: быть | G93: осуществляться | H93: путем | I93: смешанный | J93: обработка | K93: персональный | L93: данные | M93: передача | N93: получать | O93: обработка | P93: персональный | Q93: данные | R93: информация | S93: внутренний | T93: сеть | U93: нияу | V93: мифь | W93: информация | X93: доступный | Y93: лишь | Z93: строго | AA93: определенный | AB93: сотрудник | AC93: юридический | AD93: лицо | AE93: использование | AF93: сеть | AG93: общий | AH93: пользование
A94: ='данные для анализа'!A94 | B94: сбор | C94: систематизация | D94: накопление | E94: хранение | F94: уточнение | G94: обновление | H94: изменение | I94: использование | J94: распространение | K94: число | L94: передача | M94: обезличивание | N94: блокирование | O94: уничтожение | P94: персональный | Q94: данные
A95: ='данные для анализа'!A95 | B95: сбор | C95: запись | D95: систематизация | E95: накопление | F95: хранение | G95: уточнение | H95: обновление | I95: изменение | J95: извлечение | K95: использование | L95: передача | M95: распространение | N95: предоставление | O95: доступ | P95: обезличивание | Q95: блокирование | R95: удаление | S95: уничтожение
A96: ='данные для анализа'!A96 | B96: сбор | C96: накопление | D96: хранение | E96: уточнение | F96: обновление | G96: изменение | H96: систематизация | I96: использование | J96: распространение | K96: число | L96: передача | M96: обезличивание | N96: блокирование | O96: уничтожение | P96: персональный | Q96: данные | R96: необходимый | S96: ведение | T96: образовательный | U96: административно | V96: хозяйственный | W96: деятельность | X96: обмен | Y96: прием | Z96: передача | AA96: персональный | AB96: данные | AC96: между | AD96: аггпу | AE96: шукшина | AF96: третий | AG96: лицо | AH96: организация | AI96: соответствие | AJ96: заключать | AK96: между | AL96: договор | AM96: соглашение | AN96: цель | AO96: соблюдение | AP96: законный | AQ96: право | AR96: интерес | AS96: субъект | AT96: персональный | AU96: данные
A97: ='данные для анализа'!A97 | B97: сбор | C97: запись | D97: систематизация | E97: накопление | F97: хранение | G97: уточнение | H97: обновление | I97: изменение | J97: извлечение | K97: использование | L97: передача | M97: распространение | N97: предоставление | O97: доступ | P97: обезличивание | Q97: блокирование | R97: удаление | S97: уничтожение | T97: персональный | U97: данные
A98: ='данные для анализа'!A98 | B98: сбор | C98: запись | D98: систематизация | E98: накопление | F98: хранение | G98: уточнение | H98: обновление | I98: изменение | J98: извлечение | K98: использование | L98: передача | M98: число | N98: трансграничный | O98: доступ | P98: предоставление | Q98: указывать | R98: настоящее | S98: согласие | T98: организация | U98: обезличивание | V98: блокирование | W98: удаление | X98: уничтожение
A99: ='данные для анализа'!A99 | B99: неавтоматизированный | C99: обработка | D99: ведение | E99: трудовой | F99: книжка | G99: личный | H99: дело | I99: журнал | J99: отчет | K99: договор | L99: автоматизированный | M99: обработка | N99: внесение | O99: персональный | P99: данные | Q99: информационный | R99: система | S99: скуда | T99: спринт | U99: деканат | V99: операция | W99: персональный | X99: данные | Y99: сбор | Z99: хранение | AA99: накопление | AB99: уточнение | AC99: передача | AD99: уничтожение | AE99: данный
A100: ='данные для анализа'!A100 | B100: сбор | C100: запись | D100: систематизация | E100: накопление | F100: хранение | G100: уточнение | H100: обновление | I100: изменение | J100: извлечение | K100: использование | L100: передача | M100: распространение | N100: предоставление | O100: доступ | P100: блокирование | Q100: удаление | R100: уничтожение | S100: персональный | T100: данные
...

Sheet кластеры
B1: rkn:name_full | D1: сбор | E1: запись | F1: систематизация | G1: накопление | H1: хранение | I1: уточнение (обновление, изменение) | J1: извлечение | K1: использование | L1: передача (распространение, предоставление, доступ) | M1: удаление | N1: уничтожение
A2: ='данные для анализа'!A2 | B2: ='данные для анализа'!B2 | C2: =SUM(D2:V2) | D2: 1 | F2: 1 | G2: 1 | H2: 1 | I2: 1 | K2: 1 | L2: 1 | N2: 1
A3: ='данные для анализа'!A3 | B3: ='данные для анализа'!B3 | C3: =SUM(D3:V3) | D3: 1 | F3: 1 | G3: 1 | H3: 1 | I3: 1 | K3: 1 | L3: 1 | N3: 1
A4: ='данные для анализа'!A4 | B4: ='данные для анализа'!B4 | C4: =SUM(D4:V4) | D4: 1 | E4: 1 | F4: 1 | G4: 1 | H4: 1 | I4: 1 | J4: 1 | K4: 1 | L4: 1 | M4: 1 | N4: 1
A5: ='данные для анализа'!A5 | B5: ='данные для анализа'!B5 | C5: =SUM(D5:V5) | L5: 1
A6: ='данные для анализа'!A6 | B6: ='данные для анализа'!B6 | C6: =SUM(D6:V6) | D6: 1 | F6: 1 | G6: 1 | H6: 1 | I6: 1 | L6: 1 | N6: 1
A7: ='данные для анализа'!A7 | B7: ='данные для анализа'!B7 | C7: =SUM(D7:V7) | K7: 1 | L7: 1
A8: ='данные для анализа'!A8 | B8: ='данные для анализа'!B8 | C8: =SUM(D8:V8)
A9: ='данные для анализа'!A9 | B9: ='данные для анализа'!B9 | C9: =SUM(D9:V9) | D9: 1 | E9: 1 | F9: 1 | G9: 1 | H9: 1 | I9: 1 | J9: 1 | K9: 1 | L9: 1 | M9: 1 | N9: 1
A10: ='данные для анализа'!A10 | B10: ='данные для анализа'!B10 | C10: =SUM(D10:V10) | D10: 1 | E10: 1 | F10: 1 | G10: 1 | H10: 1 | I10: 1 | J10: 1 | K10: 1 | L10: 1 | M10: 1 | N10: 1
A11: ='данные для анализа'!A11 | B11: ='данные для анализа'!B11 | C11: =SUM(D11:V11) | D11: 1 | F11: 1 | G11: 1 | H11: 1 | I11: 1 | K11: 1 | L11: 1 | N11: 1
A12: ='данные для анализа'!A12 | B12: ='данные для анализа'!B12 | C12: =SUM(D12:V12) | D12: 1 | E12: 1 | F12: 1 | G12: 1 | H12: 1 | I12: 1 | J12: 1 | K12: 1 | L12: 1 | M12: 1 | N12: 1
A13: ='данные для анализа'!A13 | B13: ='данные для анализа'!B13 | C13: =SUM(D13:V13)
A14: ='данные для анализа'!A14 | B14: ='данные для анализа'!B14 | C14: =SUM(D14:V14) | K14: 1 | L14: 1
A15: ='данные для анализа'!A15 | B15: ='данные для анализа'!B15 | C15: =SUM(D15:V15) | K15: 1 | L15: 1
A16: ='данные для анализа'!A16 | B16: ='данные для анализа'!B16 | C16: =SUM(D16:V16) | K16: 1 | L16: 1
A17: ='данные для анализа'!A17 | B17: ='данные для анализа'!B17 | C17: =SUM(D17:V17) | K17: 1 | L17: 1
A18: ='данные для анализа'!A18 | B18: ='данные для анализа'!B18 | C18: =SUM(D18:V18) | D18: 1 | E18: 1 | F18: 1 | G18: 1 | H18: 1 | I18: 1 | J18: 1 | K18: 1 | L18: 1 | M18: 1 | N18: 1
A19: ='данные для анализа'!A19 | B19: ='данные для анализа'!B19 | C19: =SUM(D19:V19) | K19: 1 | L19: 1
A20: ='данные для анализа'!A20 | B20: ='данные для анализа'!B20 | C20: =SUM(D20:V20) | D20: 1 | F20: 1 | G20: 1 | H20: 1 | I20: 1 | K20: 1 | L20: 1 | N20: 1
A21: ='данные для анализа'!A21 | B21: ='данные для анализа'!B21 | C21: =SUM(D21:V21) | D21: 1 | F21: 1 | G21: 1 | H21: 1 | I21: 1 | K21: 1 | L21: 1 | N21: 1
A22: ='данные для анализа'!A22 | B22: ='данные для анализа'!B22 | C22: =SUM(D22:V22) | D22: 1 | E22: 1 | F22: 1 | G22: 1 | H22: 1 | I22: 1 | K22: 1 | M22: 1 | N22: 1
A23: ='данные для анализа'!A23 | B23: ='данные для анализа'!B23 | C23: =SUM(D23:V23) | D23: 1 | F23: 1 | G23: 1 | H23: 1 | I23: 1 | K23: 1 | L23: 1 | N23: 1
A24: ='данные для анализа'!A24 | B24: ='данные для анализа'!B24 | C24: =SUM(D24:V24) | D24: 1 | E24: 1 | F24: 1 | G24: 1 | H24: 1 | I24: 1 | J24: 1 | K24: 1 | L24: 1 | M24: 1 | N24: 1
A25: ='данные для анализа'!A25 | B25: ='данные для анализа'!B25 | C25: =SUM(D25:V25)
A26: ='данные для анализа'!A26 | B26: ='данные для анализа'!B26 | C26: =SUM(D26:V26) | D26: 1 | E26: 1 | F26: 1 | G26: 1 | H26: 1 | I26: 1 | J26: 1 | K26: 1 | L26: 1 | M26: 1 | N26: 1
A27: ='данные для анализа'!A27 | B27: ='данные для анализа'!B27 | C27: =SUM(D27:V27) | D27: 1 | E27: 1 | F27: 1 | G27: 1 | H27: 1 | I27: 1 | J27: 1 | K27: 1 | L27: 1 | M27: 1 | N27: 1
A28: ='данные для анализа'!A28 | B28: ='данные для анализа'!B28 | C28: =SUM(D28:V28) | D28: 1 | F28: 1 | G28: 1 | H28: 1 | I28: 1 | K28: 1 | L28: 1 | N28: 1
A29: ='данные для анализа'!A29 | B29: ='данные для анализа'!B29 | C29: =SUM(D29:V29)
A30: ='данные для анализа'!A30 | B30: ='данные для анализа'!B30 | C30: =SUM(D30:V30) | D30: 1 | F30: 1 | G30: 1 | H30: 1 | I30: 1 | K30: 1 | L30: 1
A31: ='данные для анализа'!A31 | B31: ='данные для анализа'!B31 | C31: =SUM(D31:V31) | D31: 1 | G31: 1 | H31: 1 | I31: 1 | K31: 1 | L31: 1 | N31: 1
A32: ='данные для анализа'!A32 | B32: ='данные для анализа'!B32 | C32: =SUM(D32:V32) | D32: 1 | E32: 1 | F32: 1 | G32: 1 | H32: 1 | I32: 1 | J32: 1 | K32: 1 | L32: 1 | M32: 1 | N32: 1
A33: ='данные для анализа'!A33 | B33: ='данные для анализа'!B33 | C33: =SUM(D33:V33) | D33: 1 | E33: 1 | F33: 1 | G33: 1 | H33: 1 | I33: 1 | J33: 1 | K33: 1 | L33: 1 | M33: 1 | N33: 1
A34: ='данные для анализа'!A34 | B34: ='данные для анализа'!B34 | C34: =SUM(D34:V34) | D34: 1 | L34: 1
A35: ='данные для анализа'!A35 | B35: ='данные для анализа'!B35 | C35: =SUM(D35:V35)
A36: ='данные для анализа'!A36 | B36: ='данные для анализа'!B36 | C36: =SUM(D36:V36) | D36: 1 | F36: 1 | G36: 1 | H36: 1 | I36: 1 | K36: 1 | L36: 1 | N36: 1
A37: ='данные для анализа'!A37 | B37: ='данные для анализа'!B37 | C37: =SUM(D37:V37) | D37: 1 | E37: 1 | F37: 1 | G37: 1 | H37: 1 | I37: 1 | J37: 1 | K37: 1 | L37: 1 | M37: 1 | N37: 1
A38: ='данные для анализа'!A38 | B38: ='данные для анализа'!B38 | C38: =SUM(D38:V38) | D38: 1 | E38: 1 | F38: 1 | G38: 1 | H38: 1 | I38: 1 | J38: 1 | K38: 1 | L38: 1 | M38: 1 | N38: 1
A39: ='данные для анализа'!A39 | B39: ='данные для анализа'!B39 | C39: =SUM(D39:V39) | D39: 1 | E39: 1 | F39: 1 | G39: 1 | H39: 1 | I39: 1 | J39: 1 | K39: 1 | L39: 1 | M39: 1 | N39: 1
A40: ='данные для анализа'!A40 | B40: ='данные для анализа'!B40 | C40: =SUM(D40:V40) | D40: 1 | E40: 1 | F40: 1 | G40: 1 | H40: 1 | I40: 1 | J40: 1 | K40: 1 | L40: 1 | M40: 1 | N40: 1
A41: ='данные для анализа'!A41 | B41: ='данные для анализа'!B41 | C41: =SUM(D41:V41) | D41: 1 | E41: 1 | F41: 1 | G41: 1 | H41: 1 | I41: 1 | J41: 1 | K41: 1 | L41: 1 | N41: 1
A42: ='данные для анализа'!A42 | B42: ='данные для анализа'!B42 | C42: =SUM(D42:V42) | D42: 1 | G42: 1 | H42: 1 | I42: 1 | K42: 1 | N42: 1
A43: ='данные для анализа'!A43 | B43: ='данные для анализа'!B43 | C43: =SUM(D43:V43) | D43: 1 | F43: 1 | G43: 1 | H43: 1 | I43: 1 | K43: 1 | N43: 1
A44: ='данные для анализа'!A44 | B44: ='данные для анализа'!B44 | C44: =SUM(D44:V44) | D44: 1 | E44: 1 | F44: 1 | G44: 1 | H44: 1 | I44: 1 | J44: 1 | K44: 1 | L44: 1 | M44: 1 | N44: 1
A45: ='данные для анализа'!A45 | B45: ='данные для анализа'!B45 | C45: =SUM(D45:V45) | D45: 1 | F45: 1 | G45: 1 | H45: 1 | I45: 1 | K45: 1 | L45: 1 | N45: 1
A46: ='данные для анализа'!A46 | B46: ='данные для анализа'!B46 | C46: =SUM(D46:V46) | D46: 1 | E46: 1 | F46: 1 | G46: 1 | H46: 1 | I46: 1 | J46: 1 | K46: 1 | L46: 1 | M46: 1 | N46: 1
A47: ='данные для анализа'!A47 | B47: ='данные для анализа'!B47 | C47: =SUM(D47:V47) | D47: 1 | F47: 1 | G47: 1 | H47: 1 | I47: 1 | L47: 1
A48: ='данные для анализа'!A48 | B48: ='данные для анализа'!B48 | C48: =SUM(D48:V48) | D48: 1 | E48: 1 | F48: 1 | G48: 1 | H48: 1 | I48: 1 | J48: 1 | K48: 1 | L48: 1 | M48: 1 | N48: 1
A49: ='данные для анализа'!A49 | B49: ='данные для анализа'!B49 | C49: =SUM(D49:V49)
A50: ='данные для анализа'!A50 | B50: ='данные для анализа'!B50 | C50: =SUM(D50:V50) | D50: 1 | F50: 1 | H50: 1
A51: ='данные для анализа'!A51 | B51: ='данные для анализа'!B51 | C51: =SUM(D51:V51) | D51: 1 | E51: 1 | F51: 1 | G51: 1 | H51: 1 | I51: 1 | K51: 1 | L51: 1 | M51: 1 | N51: 1
A52: ='данные для анализа'!A52 | B52: ='данные для анализа'!B52 | C52: =SUM(D52:V52) | D52: 1 | E52: 1 | F52: 1 | G52: 1 | H52: 1 | I52: 1 | J52: 1 | K52: 1 | L52: 1 | M52: 1 | N52: 1
A53: ='данные для анализа'!A53 | B53: ='данные для анализа'!B53 | C53: =SUM(D53:V53) | D53: 1 | E53: 1 | F53: 1 | G53: 1 | H53: 1 | I53: 1 | J53: 1 | K53: 1 | L53: 1 | M53: 1 | N53: 1
A54: ='данные для анализа'!A54 | B54: ='данные для анализа'!B54 | C54: =SUM(D54:V54) | D54: 1 | F54: 1 | G54: 1 | H54: 1 | I54: 1 | K54: 1 | L54: 1 | N54: 1
A55: ='данные для анализа'!A55 | B55: ='данные для анализа'!B55 | C55: =SUM(D55:V55) | D55: 1 | F55: 1 | G55: 1 | H55: 1 | I55: 1 | J55: 1 | K55: 1 | L55: 1 | M55: 1 | N55: 1
A56: ='данные для анализа'!A56 | B56: ='данные для анализа'!B56 | C56: =SUM(D56:V56) | D56: 1 | H56: 1 | I56: 1 | L56: 1
A57: ='данные для анализа'!A57 | B57: ='данные для анализа'!B57 | C57: =SUM(D57:V57) | D57: 1 | E57: 1 | F57: 1 | G57: 1 | H57: 1 | I57: 1 | J57: 1 | K57: 1 | L57: 1 | M57: 1 | N57: 1
A58: ='данные для анализа'!A58 | B58: ='данные для анализа'!B58 | C58: =SUM(D58:V58) | D58: 1 | F58: 1 | G58: 1 | H58: 1 | I58: 1 | K58: 1 | L58: 1 | N58: 1
A59: ='данные для анализа'!A59 | B59: ='данные для анализа'!B59 | C59: =SUM(D59:V59) | H59: 1
A60: ='данные для анализа'!A60 | B60: ='данные для анализа'!B60 | C60: =SUM(D60:V60) | D60: 1 | F60: 1 | G60: 1 | H60: 1 | I60: 1 | K60: 1 | L60: 1 | N60: 1
A61: ='данные для анализа'!A61 | B61: ='данные для анализа'!B61 | C61: =SUM(D61:V61) | D61: 1 | F61: 1 | G61: 1 | H61: 1 | I61: 1 | K61: 1 | L61: 1 | N61: 1
A62: ='данные для анализа'!A62 | B62: ='данные для анализа'!B62 | C62: =SUM(D62:V62) | D62: 1 | F62: 1 | G62: 1 | H62: 1 | I62: 1 | K62: 1 | L62: 1 | M62: 1 | N62: 1
A63: ='данные для анализа'!A63 | B63: ='данные для анализа'!B63 | C63: =SUM(D63:V63) | L63: 1
A64: ='данные для анализа'!A64 | B64: ='данные для анализа'!B64 | C64: =SUM(D64:V64) | D64: 1 | E64: 1 | F64: 1 | G64: 1 | H64: 1 | I64: 1 | J64: 1 | K64: 1 | L64: 1 | M64: 1 | N64: 1
A65: ='данные для анализа'!A65 | B65: ='данные для анализа'!B65 | C65: =SUM(D65:V65) | D65: 1 | F65: 1 | G65: 1 | H65: 1 | I65: 1 | K65: 1 | L65: 1 | N65: 1
A66: ='данные для анализа'!A66 | B66: ='данные для анализа'!B66 | C66: =SUM(D66:V66) | D66: 1 | E66: 1 | F66: 1 | G66: 1 | H66: 1 | I66: 1 | J66: 1 | K66: 1 | L66: 1 | M66: 1 | N66: 1
A67: ='данные для анализа'!A67 | B67: ='данные для анализа'!B67 | C67: =SUM(D67:V67) | L67: 1
A68: ='данные для анализа'!A68 | B68: ='данные для анализа'!B68 | C68: =SUM(D68:V68) | D68: 1 | H68: 1 | I68: 1
A69: ='данные для анализа'!A69 | B69: ='данные для анализа'!B69 | C69: =SUM(D69:V69) | D69: 1 | E69: 1 | F69: 1 | G69: 1 | H69: 1 | I69: 1 | J69: 1 | K69: 1 | L69: 1 | M69: 1 | N69: 1
A70: ='данные для анализа'!A70 | B70: ='данные для анализа'!B70 | C70: =SUM(D70:V70) | L70: 1
A71: ='данные для анализа'!A71 | B71: ='данные для анализа'!B71 | C71: =SUM(D71:V71) | F71: 1 | H71: 1 | I71: 1 | L71: 1 | N71: 1
A72: ='данные для анализа'!A72 | B72: ='данные для анализа'!B72 | C72: =SUM(D72:V72) | D72: 1 | E72: 1 | F72: 1 | G72: 1 | H72: 1 | I72: 1 | J72: 1 | K72: 1 | L72: 1 | M72: 1 | N72: 1
A73: ='данные для анализа'!A73 | B73: ='данные для анализа'!B73 | C73: =SUM(D73:V73) | D73: 1 | F73: 1 | G73: 1 | H73: 1 | I73: 1 | K73: 1 | L73: 1 | N73: 1
A74: ='данные для анализа'!A74 | B74: ='данные для анализа'!B74 | C74: =SUM(D74:V74)
A75: ='данные для анализа'!A75 | B75: ='данные для анализа'!B75 | C75: =SUM(D75:V75) | D75: 1 | F75: 1 | G75: 1 | H75: 1 | I75: 1 | K75: 1 | L75: 1 | N75: 1
A76: ='данные для анализа'!A76 | B76: ='данные для анализа'!B76 | C76: =SUM(D76:V76)
A77: ='данные для анализа'!A77 | B77: ='данные для анализа'!B77 | C77: =SUM(D77:V77) | D77: 1 | E77: 1 | F77: 1 | G77: 1 | H77: 1 | I77: 1 | K77: 1 | L77: 1 | M77: 1 | N77: 1
A78: ='данные для анализа'!A78 | B78: ='данные для анализа'!B78 | C78: =SUM(D78:V78) | D78: 1 | E78: 1 | F78: 1 | G78: 1 | H78: 1 | I78: 1 | J78: 1 | K78: 1 | L78: 1 | M78: 1 | N78: 1
A79: ='данные для анализа'!A79 | B79: ='данные для анализа'!B79 | C79: =SUM(D79:V79) | D79: 1 | E79: 1 | F79: 1 | G79: 1 | H79: 1 | I79: 1 | J79: 1 | K79: 1 | L79: 1 | M79: 1 | N79: 1
A80: ='данные для анализа'!A80 | B80: ='данные для анализа'!B80 | C80: =SUM(D80:V80) | D80: 1 | E80: 1 | F80: 1 | G80: 1 | H80: 1 | I80: 1 | J80: 1 | K80: 1 | L80: 1 | M80: 1 | N80: 1
A81: ='данные для анализа'!A81 | B81: ='данные для анализа'!B81 | C81: =SUM(D81:V81) | D81: 1 | E81: 1 | F81: 1 | G81: 1 | H81: 1 | I81: 1 | J81: 1 | K81: 1 | L81: 1 | M81: 1 | N81: 1
A82: ='данные для анализа'!A82 | B82: ='данные для анализа'!B82 | C82: =SUM(D82:V82) | D82: 1 | H82: 1 | I82: 1 | L82: 1 | N82: 1
A83: ='данные для анализа'!A83 | B83: ='данные для анализа'!B83 | C83: =SUM(D83:V83) | D83: 1 | E83: 1 | G83: 1 | H83: 1 | I83: 1
A84: ='данные для анализа'!A84 | B84: ='данные для анализа'!B84 | C84: =SUM(D84:V84) | D84: 1 | E84: 1 | F84: 1 | G84: 1 | H84: 1 | I84: 1 | J84: 1 | K84: 1 | L84: 1 | M84: 1 | N84: 1
A85: ='данные для анализа'!A85 | B85: ='данные для анализа'!B85 | C85: =SUM(D85:V85) | D85: 1 | I85: 1 | L85: 1 | N85: 1
A86: ='данные для анализа'!A86 | B86: ='данные для анализа'!B86 | C86: =SUM(D86:V86) | D86: 1 | F86: 1 | G86: 1 | H86: 1 | I86: 1 | K86: 1 | L86: 1 | N86: 1
A87: ='данные для анализа'!A87 | B87: ='данные для анализа'!B87 | C87: =SUM(D87:V87) | D87: 1 | E87: 1 | F87: 1 | G87: 1 | H87: 1 | I87: 1 | K87: 1 | L87: 1 | M87: 1 | N87: 1
A88: ='данные для анализа'!A88 | B88: ='данные для анализа'!B88 | C88: =SUM(D88:V88) | D88: 1 | E88: 1 | F88: 1 | G88: 1 | H88: 1 | I88: 1 | K88: 1 | L88: 1 | M88: 1 | N88: 1
A89: ='данные для анализа'!A89 | B89: ='данные для анализа'!B89 | C89: =SUM(D89:V89) | D89: 1 | E89: 1 | F89: 1 | G89: 1 | H89: 1 | I89: 1 | J89: 1 | K89: 1 | M89: 1 | N89: 1
A90: ='данные для анализа'!A90 | B90: ='данные для анализа'!B90 | C90: =SUM(D90:V90) | D90: 1 | E90: 1 | F90: 1 | G90: 1 | H90: 1 | I90: 1 | J90: 1 | K90: 1 | L90: 1 | M90: 1 | N90: 1
A91: ='данные для анализа'!A91 | B91: ='данные для анализа'!B91 | C91: =SUM(D91:V91) | D91: 1 | E91: 1 | H91: 1 | I91: 1 | K91: 1 | L91: 1 | M91: 1
A92: ='данные для анализа'!A92 | B92: ='данные для анализа'!B92 | C92: =SUM(D92:V92) | D92: 1 | F92: 1 | G92: 1 | H92: 1 | I92: 1 | K92: 1 | L92: 1 | N92: 1
A93: ='данные для анализа'!A93 | B93: ='данные для анализа'!B93 | C93: =SUM(D93:V93) | K93: 1 | L93: 1
A94: ='данные для анализа'!A94 | B94: ='данные для анализа'!B94 | C94: =SUM(D94:V94) | D94: 1 | F94: 1 | G94: 1 | H94: 1 | I94: 1 | K94: 1 | L94: 1 | N94: 1
A95: ='данные для анализа'!A95 | B95: ='данные для анализа'!B95 | C95: =SUM(D95:V95) | D95: 1 | E95: 1 | F95: 1 | G95: 1 | H95: 1 | I95: 1 | J95: 1 | K95: 1 | L95: 1 | M95: 1 | N95: 1
A96: ='данные для анализа'!A96 | B96: ='данные для анализа'!B96 | C96: =SUM(D96:V96) | D96: 1 | F96: 1 | G96: 1 | H96: 1 | I96: 1 | K96: 1 | L96: 1 | N96: 1
A97: ='данные для анализа'!A97 | B97: ='данные для анализа'!B97 | C97: =SUM(D97:V97) | D97: 1 | E97: 1 | F97: 1 | G97: 1 | H97: 1 | I97: 1 | J97: 1 | K97: 1 | L97: 1 | M97: 1 | N97: 1
A98: ='данные для анализа'!A98 | B98: ='данные для анализа'!B98 | C98: =SUM(D98:V98) | D98: 1 | E98: 1 | F98: 1 | G98: 1 | H98: 1 | I98: 1 | J98: 1 | K98: 1 | L98: 1 | M98: 1 | N98: 1
A99: ='данные для анализа'!A99 | B99: ='данные для анализа'!B99 | C99: =SUM(D99:V99) | D99: 1 | G99: 1 | H99: 1 | I99: 1 | L99: 1 | N99: 1
A100: ='данные для анализа'!A100 | B100: ='данные для анализа'!B100 | C100: =SUM(D100:V100) | D100: 1 | E100: 1 | F100: 1 | G100: 1 | H100: 1 | I100: 1 | J100: 1 | K100: 1 | L100: 1 | M100: 1 | N100: 1
...
